Workbook

Sheet List
A1: סימול | B1: שם | C1: מחלקה | D1: תווית | E1: מספר כישלונות | F1: 1 רווחיות | G1: 2 תזרים | H1: 3 תשואה על ההון | I1: 4 מאזן | J1: 5 צמיחה | K1: 6 דילול | L1: סיבת הכישלון | M1: Risk Tier | N1: תקרת פוזיציה CORE | O1: Cheap Score | P1: רבעון זול | Q1: SMA200 עולה | R1: Cheap Score שמיש לשיטה | S1: שווי מול עצמה | T1: P/E מול חציון עצמי | U1: FCF yield | V1: ADR60 | W1: Max DD (5 שנים)
A2: =Data!A2 -> ABNB | B2: =Data!B2 -> Airbnb Inc. | C2: =Data!F2 -> STD | D2: =IF(E2=0,"CORE",IF(E2=1,"WATCH","NON-CORE")) -> CORE | E2: =COUNTIF(F2:K2,"FAIL") -> 0 | F2: =IF(C2="FIN",IF(Data!M2=Data!H2,"PASS","FAIL"),IF(AND(ISNUMBER(Data!L2),Data!L2>=Rules!$B$5,IF(Data!H2<5,Data!M2=Data!H2,Data!M2>=Rules!$B$6)),"PASS","FAIL")) -> PASS | G2: =IF(C2="FIN","n/a",IF(C2="UTIL/REIT",IF(Data!Q2=Data!H2,"PASS","FAIL"),IF(AND(ISNUMBER(Data!N2),Data!N2>0,IF(Data!H2<5,Data!P2=Data!H2,Data!P2>=Rules!$B$7)),"PASS","FAIL"))) -> PASS | H2: =IF(C2="FIN",IF(AND(ISNUMBER(Data!S2),Data!S2>=Rules!$B$15),"PASS","FAIL"),IF(AND(ISNUMBER(Data!R2),Data!R2>=Rules!$B$8),"PASS","FAIL")) -> PASS | I2: =IF(C2="FIN","n/a",IF(C2="UTIL/REIT",IF(AND(Data!U2<=Rules!$B$16,Data!V2>=Rules!$B$17),"PASS","FAIL"),IF(AND(Data!U2<=Rules!$B$9,Data!V2>=Rules!$B$10),"PASS","FAIL"))) -> PASS | J2: =IF(AND(ISNUMBER(Data!J2),ISNUMBER(Data!K2)),IF(AND(Data!J2>=Rules!$B$11,Data!K2>=Rules!$B$12),"PASS","FAIL"),"FAIL") -> PASS | K2: =IF(AND(ISNUMBER(Data!W2),ISNUMBER(Data!X2)),IF(AND(Data!W2<=Rules!$B$13,Data!X2<=Rules!$B$14),"PASS","FAIL"),"FAIL") -> PASS | L2: =IF(F2="FAIL","רווחיות; ","")&IF(G2="FAIL","תזרים; ","")&IF(H2="FAIL","תשואה על ההון; ","")&IF(I2="FAIL","מאזן; ","")&IF(J2="FAIL","צמיחה; ","")&IF(K2="FAIL","דילול; ","") | M2: HIGH | N2: =IF(M2="EXTREME",Rules!$B$23,IF(M2="HIGH",Rules!$B$22,Rules!$B$21)) -> 0.06 | O2: 31.350718 | P2: Q2 | Q2: כן | R2: =IF(Q2="כן",P2,"לא רלוונטי (SMA200 יורד)") -> Q2 | S2: =IF(NOT(ISNUMBER(T2)),"n/a",IF(AND(T2>Rules!$B$18,ISNUMBER(U2),U2<Rules!$B$19),"יקרה",IF(T2<Rules!$B$20,"זולה","הוגנת"))) -> הוגנת | T2: =Data!AA2 -> 1.2345654 | U2: =Data!AC2 -> 0.049967079 | V2: 0.0297 | W2: -0.6023
A3: =Data!A3 -> ADBE | B3: =Data!B3 -> Adobe Inc. | C3: =Data!F3 -> STD | D3: =IF(E3=0,"CORE",IF(E3=1,"WATCH","NON-CORE")) -> CORE | E3: =COUNTIF(F3:K3,"FAIL") -> 0 | F3: =IF(C3="FIN",IF(Data!M3=Data!H3,"PASS","FAIL"),IF(AND(ISNUMBER(Data!L3),Data!L3>=Rules!$B$5,IF(Data!H3<5,Data!M3=Data!H3,Data!M3>=Rules!$B$6)),"PASS","FAIL")) -> PASS | G3: =IF(C3="FIN","n/a",IF(C3="UTIL/REIT",IF(Data!Q3=Data!H3,"PASS","FAIL"),IF(AND(ISNUMBER(Data!N3),Data!N3>0,IF(Data!H3<5,Data!P3=Data!H3,Data!P3>=Rules!$B$7)),"PASS","FAIL"))) -> PASS | H3: =IF(C3="FIN",IF(AND(ISNUMBER(Data!S3),Data!S3>=Rules!$B$15),"PASS","FAIL"),IF(AND(ISNUMBER(Data!R3),Data!R3>=Rules!$B$8),"PASS","FAIL")) -> PASS | I3: =IF(C3="FIN","n/a",IF(C3="UTIL/REIT",IF(AND(Data!U3<=Rules!$B$16,Data!V3>=Rules!$B$17),"PASS","FAIL"),IF(AND(Data!U3<=Rules!$B$9,Data!V3>=Rules!$B$10),"PASS","FAIL"))) -> PASS | J3: =IF(AND(ISNUMBER(Data!J3),ISNUMBER(Data!K3)),IF(AND(Data!J3>=Rules!$B$11,Data!K3>=Rules!$B$12),"PASS","FAIL"),"FAIL") -> PASS | K3: =IF(AND(ISNUMBER(Data!W3),ISNUMBER(Data!X3)),IF(AND(Data!W3<=Rules!$B$13,Data!X3<=Rules!$B$14),"PASS","FAIL"),"FAIL") -> PASS | L3: =IF(F3="FAIL","רווחיות; ","")&IF(G3="FAIL","תזרים; ","")&IF(H3="FAIL","תשואה על ההון; ","")&IF(I3="FAIL","מאזן; ","")&IF(J3="FAIL","צמיחה; ","")&IF(K3="FAIL","דילול; ","") | M3: EXTREME | N3: =IF(M3="EXTREME",Rules!$B$23,IF(M3="HIGH",Rules!$B$22,Rules!$B$21)) -> 0.03 | O3: 53.644553 | P3: Q3 | Q3: לא | R3: =IF(Q3="כן",P3,"לא רלוונטי (SMA200 יורד)") -> לא רלוונטי (SMA200 יורד) | S3: =IF(NOT(ISNUMBER(T3)),"n/a",IF(AND(T3>Rules!$B$18,ISNUMBER(U3),U3<Rules!$B$19),"יקרה",IF(T3<Rules!$B$20,"זולה","הוגנת"))) -> זולה | T3: =Data!AA3 -> 0.31880781 | U3: =Data!AC3 -> 0.11595158 | V3: 0.0366 | W3: -0.7189
A4: =Data!A4 -> ADP | B4: =Data!B4 -> Automatic Data Processing Inc. | C4: =Data!F4 -> STD | D4: =IF(E4=0,"CORE",IF(E4=1,"WATCH","NON-CORE")) -> CORE | E4: =COUNTIF(F4:K4,"FAIL") -> 0 | F4: =IF(C4="FIN",IF(Data!M4=Data!H4,"PASS","FAIL"),IF(AND(ISNUMBER(Data!L4),Data!L4>=Rules!$B$5,IF(Data!H4<5,Data!M4=Data!H4,Data!M4>=Rules!$B$6)),"PASS","FAIL")) -> PASS | G4: =IF(C4="FIN","n/a",IF(C4="UTIL/REIT",IF(Data!Q4=Data!H4,"PASS","FAIL"),IF(AND(ISNUMBER(Data!N4),Data!N4>0,IF(Data!H4<5,Data!P4=Data!H4,Data!P4>=Rules!$B$7)),"PASS","FAIL"))) -> PASS | H4: =IF(C4="FIN",IF(AND(ISNUMBER(Data!S4),Data!S4>=Rules!$B$15),"PASS","FAIL"),IF(AND(ISNUMBER(Data!R4),Data!R4>=Rules!$B$8),"PASS","FAIL")) -> PASS | I4: =IF(C4="FIN","n/a",IF(C4="UTIL/REIT",IF(AND(Data!U4<=Rules!$B$16,Data!V4>=Rules!$B$17),"PASS","FAIL"),IF(AND(Data!U4<=Rules!$B$9,Data!V4>=Rules!$B$10),"PASS","FAIL"))) -> PASS | J4: =IF(AND(ISNUMBER(Data!J4),ISNUMBER(Data!K4)),IF(AND(Data!J4>=Rules!$B$11,Data!K4>=Rules!$B$12),"PASS","FAIL"),"FAIL") -> PASS | K4: =IF(AND(ISNUMBER(Data!W4),ISNUMBER(Data!X4)),IF(AND(Data!W4<=Rules!$B$13,Data!X4<=Rules!$B$14),"PASS","FAIL"),"FAIL") -> PASS | L4: =IF(F4="FAIL","רווחיות; ","")&IF(G4="FAIL","תזרים; ","")&IF(H4="FAIL","תשואה על ההון; ","")&IF(I4="FAIL","מאזן; ","")&IF(J4="FAIL","צמיחה; ","")&IF(K4="FAIL","דילול; ","") | M4: MEDIUM | N4: =IF(M4="EXTREME",Rules!$B$23,IF(M4="HIGH",Rules!$B$22,Rules!$B$21)) -> 0.1 | O4: 44.591367 | P4: Q2 | Q4: כן | R4: =IF(Q4="כן",P4,"לא רלוונטי (SMA200 יורד)") -> Q2 | S4: =IF(NOT(ISNUMBER(T4)),"n/a",IF(AND(T4>Rules!$B$18,ISNUMBER(U4),U4<Rules!$B$19),"יקרה",IF(T4<Rules!$B$20,"זולה","הוגנת"))) -> הוגנת | T4: =Data!AA4 -> 0.94277549 | U4: =Data!AC4 -> 0.045209355 | V4: 0.0222 | W4: -0.4223
A5: =Data!A5 -> ANET | B5: =Data!B5 -> Arista Networks Inc. | C5: =Data!F5 -> STD | D5: =IF(E5=0,"CORE",IF(E5=1,"WATCH","NON-CORE")) -> CORE | E5: =COUNTIF(F5:K5,"FAIL") -> 0 | F5: =IF(C5="FIN",IF(Data!M5=Data!H5,"PASS","FAIL"),IF(AND(ISNUMBER(Data!L5),Data!L5>=Rules!$B$5,IF(Data!H5<5,Data!M5=Data!H5,Data!M5>=Rules!$B$6)),"PASS","FAIL")) -> PASS | G5: =IF(C5="FIN","n/a",IF(C5="UTIL/REIT",IF(Data!Q5=Data!H5,"PASS","FAIL"),IF(AND(ISNUMBER(Data!N5),Data!N5>0,IF(Data!H5<5,Data!P5=Data!H5,Data!P5>=Rules!$B$7)),"PASS","FAIL"))) -> PASS | H5: =IF(C5="FIN",IF(AND(ISNUMBER(Data!S5),Data!S5>=Rules!$B$15),"PASS","FAIL"),IF(AND(ISNUMBER(Data!R5),Data!R5>=Rules!$B$8),"PASS","FAIL")) -> PASS | I5: =IF(C5="FIN","n/a",IF(C5="UTIL/REIT",IF(AND(Data!U5<=Rules!$B$16,Data!V5>=Rules!$B$17),"PASS","FAIL"),IF(AND(Data!U5<=Rules!$B$9,Data!V5>=Rules!$B$10),"PASS","FAIL"))) -> PASS | J5: =IF(AND(ISNUMBER(Data!J5),ISNUMBER(Data!K5)),IF(AND(Data!J5>=Rules!$B$11,Data!K5>=Rules!$B$12),"PASS","FAIL"),"FAIL") -> PASS | K5: =IF(AND(ISNUMBER(Data!W5),ISNUMBER(Data!X5)),IF(AND(Data!W5<=Rules!$B$13,Data!X5<=Rules!$B$14),"PASS","FAIL"),"FAIL") -> PASS | L5: =IF(F5="FAIL","רווחיות; ","")&IF(G5="FAIL","תזרים; ","")&IF(H5="FAIL","תשואה על ההון; ","")&IF(I5="FAIL","מאזן; ","")&IF(J5="FAIL","צמיחה; ","")&IF(K5="FAIL","דילול; ","") | M5: EXTREME | N5: =IF(M5="EXTREME",Rules!$B$23,IF(M5="HIGH",Rules!$B$22,Rules!$B$21)) -> 0.03 | O5: 27.546126 | P5: Q2 | Q5: כן | R5: =IF(Q5="כן",P5,"לא רלוונטי (SMA200 יורד)") -> Q2 | S5: =IF(NOT(ISNUMBER(T5)),"n/a",IF(AND(T5>Rules!$B$18,ISNUMBER(U5),U5<Rules!$B$19),"יקרה",IF(T5<Rules!$B$20,"זולה","הוגנת"))) -> יקרה | T5: =Data!AA5 -> 1.3988264 | U5: =Data!AC5 -> 0.019414865 | V5: 0.0422 | W5: -0.5043
A6: =Data!A6 -> APH | B6: =Data!B6 -> Amphenol Corp. | C6: =Data!F6 -> STD | D6: =IF(E6=0,"CORE",IF(E6=1,"WATCH","NON-CORE")) -> CORE | E6: =COUNTIF(F6:K6,"FAIL") -> 0 | F6: =IF(C6="FIN",IF(Data!M6=Data!H6,"PASS","FAIL"),IF(AND(ISNUMBER(Data!L6),Data!L6>=Rules!$B$5,IF(Data!H6<5,Data!M6=Data!H6,Data!M6>=Rules!$B$6)),"PASS","FAIL")) -> PASS | G6: =IF(C6="FIN","n/a",IF(C6="UTIL/REIT",IF(Data!Q6=Data!H6,"PASS","FAIL"),IF(AND(ISNUMBER(Data!N6),Data!N6>0,IF(Data!H6<5,Data!P6=Data!H6,Data!P6>=Rules!$B$7)),"PASS","FAIL"))) -> PASS | H6: =IF(C6="FIN",IF(AND(ISNUMBER(Data!S6),Data!S6>=Rules!$B$15),"PASS","FAIL"),IF(AND(ISNUMBER(Data!R6),Data!R6>=Rules!$B$8),"PASS","FAIL")) -> PASS | I6: =IF(C6="FIN","n/a",IF(C6="UTIL/REIT",IF(AND(Data!U6<=Rules!$B$16,Data!V6>=Rules!$B$17),"PASS","FAIL"),IF(AND(Data!U6<=Rules!$B$9,Data!V6>=Rules!$B$10),"PASS","FAIL"))) -> PASS | J6: =IF(AND(ISNUMBER(Data!J6),ISNUMBER(Data!K6)),IF(AND(Data!J6>=Rules!$B$11,Data!K6>=Rules!$B$12),"PASS","FAIL"),"FAIL") -> PASS | K6: =IF(AND(ISNUMBER(Data!W6),ISNUMBER(Data!X6)),IF(AND(Data!W6<=Rules!$B$13,Data!X6<=Rules!$B$14),"PASS","FAIL"),"FAIL") -> PASS | L6: =IF(F6="FAIL","רווחיות; ","")&IF(G6="FAIL","תזרים; ","")&IF(H6="FAIL","תשואה על ההון; ","")&IF(I6="FAIL","מאזן; ","")&IF(J6="FAIL","צמיחה; ","")&IF(K6="FAIL","דילול; ","") | M6: HIGH | N6: =IF(M6="EXTREME",Rules!$B$23,IF(M6="HIGH",Rules!$B$22,Rules!$B$21)) -> 0.06 | O6: 45.708087 | P6: Q2 | Q6: כן | R6: =IF(Q6="כן",P6,"לא רלוונטי (SMA200 יורד)") -> Q2 | S6: =IF(NOT(ISNUMBER(T6)),"n/a",IF(AND(T6>Rules!$B$18,ISNUMBER(U6),U6<Rules!$B$19),"יקרה",IF(T6<Rules!$B$20,"זולה","הוגנת"))) -> הוגנת | T6: =Data!AA6 -> 1.2297439 | U6: =Data!AC6 -> 0.022177829 | V6: 0.0335 | W6: -0.2887
A7: =Data!A7 -> APP | B7: =Data!B7 -> AppLovin Corp. | C7: =Data!F7 -> STD | D7: =IF(E7=0,"CORE",IF(E7=1,"WATCH","NON-CORE")) -> CORE | E7: =COUNTIF(F7:K7,"FAIL") -> 0 | F7: =IF(C7="FIN",IF(Data!M7=Data!H7,"PASS","FAIL"),IF(AND(ISNUMBER(Data!L7),Data!L7>=Rules!$B$5,IF(Data!H7<5,Data!M7=Data!H7,Data!M7>=Rules!$B$6)),"PASS","FAIL")) -> PASS | G7: =IF(C7="FIN","n/a",IF(C7="UTIL/REIT",IF(Data!Q7=Data!H7,"PASS","FAIL"),IF(AND(ISNUMBER(Data!N7),Data!N7>0,IF(Data!H7<5,Data!P7=Data!H7,Data!P7>=Rules!$B$7)),"PASS","FAIL"))) -> PASS | H7: =IF(C7="FIN",IF(AND(ISNUMBER(Data!S7),Data!S7>=Rules!$B$15),"PASS","FAIL"),IF(AND(ISNUMBER(Data!R7),Data!R7>=Rules!$B$8),"PASS","FAIL")) -> PASS | I7: =IF(C7="FIN","n/a",IF(C7="UTIL/REIT",IF(AND(Data!U7<=Rules!$B$16,Data!V7>=Rules!$B$17),"PASS","FAIL"),IF(AND(Data!U7<=Rules!$B$9,Data!V7>=Rules!$B$10),"PASS","FAIL"))) -> PASS | J7: =IF(AND(ISNUMBER(Data!J7),ISNUMBER(Data!K7)),IF(AND(Data!J7>=Rules!$B$11,Data!K7>=Rules!$B$12),"PASS","FAIL"),"FAIL") -> PASS | K7: =IF(AND(ISNUMBER(Data!W7),ISNUMBER(Data!X7)),IF(AND(Data!W7<=Rules!$B$13,Data!X7<=Rules!$B$14),"PASS","FAIL"),"FAIL") -> PASS | L7: =IF(F7="FAIL","רווחיות; ","")&IF(G7="FAIL","תזרים; ","")&IF(H7="FAIL","תשואה על ההון; ","")&IF(I7="FAIL","מאזן; ","")&IF(J7="FAIL","צמיחה; ","")&IF(K7="FAIL","דילול; ","") | M7: EXTREME | N7: =IF(M7="EXTREME",Rules!$B$23,IF(M7="HIGH",Rules!$B$22,Rules!$B$21)) -> 0.03 | O7: 84.490415 | P7: Q4 | Q7: לא | R7: =IF(Q7="כן",P7,"לא רלוונטי (SMA200 יורד)") -> לא רלוונטי (SMA200 יורד) | S7: =IF(NOT(ISNUMBER(T7)),"n/a",IF(AND(T7>Rules!$B$18,ISNUMBER(U7),U7<Rules!$B$19),"יקרה",IF(T7<Rules!$B$20,"זולה","הוגנת"))) -> זולה | T7: =Data!AA7 -> 0.30107134 | U7: =Data!AC7 -> 0.049444747 | V7: 0.0464 | W7: -0.9195
A8: =Data!A8 -> ASML | B8: =Data!B8 -> ASML Holding N.V. | C8: =Data!F8 -> STD | D8: =IF(E8=0,"CORE",IF(E8=1,"WATCH","NON-CORE")) -> CORE | E8: =COUNTIF(F8:K8,"FAIL") -> 0 | F8: =IF(C8="FIN",IF(Data!M8=Data!H8,"PASS","FAIL"),IF(AND(ISNUMBER(Data!L8),Data!L8>=Rules!$B$5,IF(Data!H8<5,Data!M8=Data!H8,Data!M8>=Rules!$B$6)),"PASS","FAIL")) -> PASS | G8: =IF(C8="FIN","n/a",IF(C8="UTIL/REIT",IF(Data!Q8=Data!H8,"PASS","FAIL"),IF(AND(ISNUMBER(Data!N8),Data!N8>0,IF(Data!H8<5,Data!P8=Data!H8,Data!P8>=Rules!$B$7)),"PASS","FAIL"))) -> PASS | H8: =IF(C8="FIN",IF(AND(ISNUMBER(Data!S8),Data!S8>=Rules!$B$15),"PASS","FAIL"),IF(AND(ISNUMBER(Data!R8),Data!R8>=Rules!$B$8),"PASS","FAIL")) -> PASS | I8: =IF(C8="FIN","n/a",IF(C8="UTIL/REIT",IF(AND(Data!U8<=Rules!$B$16,Data!V8>=Rules!$B$17),"PASS","FAIL"),IF(AND(Data!U8<=Rules!$B$9,Data!V8>=Rules!$B$10),"PASS","FAIL"))) -> PASS | J8: =IF(AND(ISNUMBER(Data!J8),ISNUMBER(Data!K8)),IF(AND(Data!J8>=Rules!$B$11,Data!K8>=Rules!$B$12),"PASS","FAIL"),"FAIL") -> PASS | K8: =IF(AND(ISNUMBER(Data!W8),ISNUMBER(Data!X8)),IF(AND(Data!W8<=Rules!$B$13,Data!X8<=Rules!$B$14),"PASS","FAIL"),"FAIL") -> PASS | L8: =IF(F8="FAIL","רווחיות; ","")&IF(G8="FAIL","תזרים; ","")&IF(H8="FAIL","תשואה על ההון; ","")&IF(I8="FAIL","מאזן; ","")&IF(J8="FAIL","צמיחה; ","")&IF(K8="FAIL","דילול; ","") | M8: HIGH | N8: =IF(M8="EXTREME",Rules!$B$23,IF(M8="HIGH",Rules!$B$22,Rules!$B$21)) -> 0.06 | O8: 40.730664 | P8: Q2 | Q8: כן | R8: =IF(Q8="כן",P8,"לא רלוונטי (SMA200 יורד)") -> Q2 | S8: =IF(NOT(ISNUMBER(T8)),"n/a",IF(AND(T8>Rules!$B$18,ISNUMBER(U8),U8<Rules!$B$19),"יקרה",IF(T8<Rules!$B$20,"זולה","הוגנת"))) -> יקרה | T8: =Data!AA8 -> 1.5359206 | U8: =Data!AC8 -> 0.016987946 | V8: 0.0281 | W8: -0.5684
A9: =Data!A9 -> AXP | B9: =Data!B9 -> American Express Co. | C9: =Data!F9 -> FIN | D9: =IF(E9=0,"CORE",IF(E9=1,"WATCH","NON-CORE")) -> CORE | E9: =COUNTIF(F9:K9,"FAIL") -> 0 | F9: =IF(C9="FIN",IF(Data!M9=Data!H9,"PASS","FAIL"),IF(AND(ISNUMBER(Data!L9),Data!L9>=Rules!$B$5,IF(Data!H9<5,Data!M9=Data!H9,Data!M9>=Rules!$B$6)),"PASS","FAIL")) -> PASS | G9: =IF(C9="FIN","n/a",IF(C9="UTIL/REIT",IF(Data!Q9=Data!H9,"PASS","FAIL"),IF(AND(ISNUMBER(Data!N9),Data!N9>0,IF(Data!H9<5,Data!P9=Data!H9,Data!P9>=Rules!$B$7)),"PASS","FAIL"))) -> n/a | H9: =IF(C9="FIN",IF(AND(ISNUMBER(Data!S9),Data!S9>=Rules!$B$15),"PASS","FAIL"),IF(AND(ISNUMBER(Data!R9),Data!R9>=Rules!$B$8),"PASS","FAIL")) -> PASS | I9: =IF(C9="FIN","n/a",IF(C9="UTIL/REIT",IF(AND(Data!U9<=Rules!$B$16,Data!V9>=Rules!$B$17),"PASS","FAIL"),IF(AND(Data!U9<=Rules!$B$9,Data!V9>=Rules!$B$10),"PASS","FAIL"))) -> n/a | J9: =IF(AND(ISNUMBER(Data!J9),ISNUMBER(Data!K9)),IF(AND(Data!J9>=Rules!$B$11,Data!K9>=Rules!$B$12),"PASS","FAIL"),"FAIL") -> PASS | K9: =IF(AND(ISNUMBER(Data!W9),ISNUMBER(Data!X9)),IF(AND(Data!W9<=Rules!$B$13,Data!X9<=Rules!$B$14),"PASS","FAIL"),"FAIL") -> PASS | L9: =IF(F9="FAIL","רווחיות; ","")&IF(G9="FAIL","תזרים; ","")&IF(H9="FAIL","תשואה על ההון; ","")&IF(I9="FAIL","מאזן; ","")&IF(J9="FAIL","צמיחה; ","")&IF(K9="FAIL","דילול; ","") | M9: MEDIUM | N9: =IF(M9="EXTREME",Rules!$B$23,IF(M9="HIGH",Rules!$B$22,Rules!$B$21)) -> 0.1 | O9: 91.516139 | P9: Q4 | Q9: לא | R9: =IF(Q9="כן",P9,"לא רלוונטי (SMA200 יורד)") -> לא רלוונטי (SMA200 יורד) | S9: =IF(NOT(ISNUMBER(T9)),"n/a",IF(AND(T9>Rules!$B$18,ISNUMBER(U9),U9<Rules!$B$19),"יקרה",IF(T9<Rules!$B$20,"זולה","הוגנת"))) -> הוגנת | T9: =Data!AA9 -> 1.1324746 | U9: =Data!AC9 -> 0.072181816 | V9: 0.018 | W9: -0.3198
A10: =Data!A10 -> BAC | B10: =Data!B10 -> Bank of America Corp. | C10: =Data!F10 -> FIN | D10: =IF(E10=0,"CORE",IF(E10=1,"WATCH","NON-CORE")) -> CORE | E10: =COUNTIF(F10:K10,"FAIL") -> 0 | F10: =IF(C10="FIN",IF(Data!M10=Data!H10,"PASS","FAIL"),IF(AND(ISNUMBER(Data!L10),Data!L10>=Rules!$B$5,IF(Data!H10<5,Data!M10=Data!H10,Data!M10>=Rules!$B$6)),"PASS","FAIL")) -> PASS | G10: =IF(C10="FIN","n/a",IF(C10="UTIL/REIT",IF(Data!Q10=Data!H10,"PASS","FAIL"),IF(AND(ISNUMBER(Data!N10),Data!N10>0,IF(Data!H10<5,Data!P10=Data!H10,Data!P10>=Rules!$B$7)),"PASS","FAIL"))) -> n/a | H10: =IF(C10="FIN",IF(AND(ISNUMBER(Data!S10),Data!S10>=Rules!$B$15),"PASS","FAIL"),IF(AND(ISNUMBER(Data!R10),Data!R10>=Rules!$B$8),"PASS","FAIL")) -> PASS | I10: =IF(C10="FIN","n/a",IF(C10="UTIL/REIT",IF(AND(Data!U10<=Rules!$B$16,Data!V10>=Rules!$B$17),"PASS","FAIL"),IF(AND(Data!U10<=Rules!$B$9,Data!V10>=Rules!$B$10),"PASS","FAIL"))) -> n/a | J10: =IF(AND(ISNUMBER(Data!J10),ISNUMBER(Data!K10)),IF(AND(Data!J10>=Rules!$B$11,Data!K10>=Rules!$B$12),"PASS","FAIL"),"FAIL") -> PASS | K10: =IF(AND(ISNUMBER(Data!W10),ISNUMBER(Data!X10)),IF(AND(Data!W10<=Rules!$B$13,Data!X10<=Rules!$B$14),"PASS","FAIL"),"FAIL") -> PASS | L10: =IF(F10="FAIL","רווחיות; ","")&IF(G10="FAIL","תזרים; ","")&IF(H10="FAIL","תשואה על ההון; ","")&IF(I10="FAIL","מאזן; ","")&IF(J10="FAIL","צמיחה; ","")&IF(K10="FAIL","דילול; ","") | M10: MEDIUM | N10: =IF(M10="EXTREME",Rules!$B$23,IF(M10="HIGH",Rules!$B$22,Rules!$B$21)) -> 0.1 | O10: 74.53075 | P10: Q3 | Q10: כן | R10: =IF(Q10="כן",P10,"לא רלוונטי (SMA200 יורד)") -> Q3 | S10: =IF(NOT(ISNUMBER(T10)),"n/a",IF(AND(T10>Rules!$B$18,ISNUMBER(U10),U10<Rules!$B$19),"יקרה",IF(T10<Rules!$B$20,"זולה","הוגנת"))) -> הוגנת | T10: =Data!AA10 -> 0.99770185 | U10: =Data!AC10 -> 0.24552378 | V10: 0.0185 | W10: -0.4903
A11: =Data!A11 -> BKNG | B11: =Data!B11 -> Booking Holdings Inc. | C11: =Data!F11 -> STD | D11: =IF(E11=0,"CORE",IF(E11=1,"WATCH","NON-CORE")) -> CORE | E11: =COUNTIF(F11:K11,"FAIL") -> 0 | F11: =IF(C11="FIN",IF(Data!M11=Data!H11,"PASS","FAIL"),IF(AND(ISNUMBER(Data!L11),Data!L11>=Rules!$B$5,IF(Data!H11<5,Data!M11=Data!H11,Data!M11>=Rules!$B$6)),"PASS","FAIL")) -> PASS | G11: =IF(C11="FIN","n/a",IF(C11="UTIL/REIT",IF(Data!Q11=Data!H11,"PASS","FAIL"),IF(AND(ISNUMBER(Data!N11),Data!N11>0,IF(Data!H11<5,Data!P11=Data!H11,Data!P11>=Rules!$B$7)),"PASS","FAIL"))) -> PASS | H11: =IF(C11="FIN",IF(AND(ISNUMBER(Data!S11),Data!S11>=Rules!$B$15),"PASS","FAIL"),IF(AND(ISNUMBER(Data!R11),Data!R11>=Rules!$B$8),"PASS","FAIL")) -> PASS | I11: =IF(C11="FIN","n/a",IF(C11="UTIL/REIT",IF(AND(Data!U11<=Rules!$B$16,Data!V11>=Rules!$B$17),"PASS","FAIL"),IF(AND(Data!U11<=Rules!$B$9,Data!V11>=Rules!$B$10),"PASS","FAIL"))) -> PASS | J11: =IF(AND(ISNUMBER(Data!J11),ISNUMBER(Data!K11)),IF(AND(Data!J11>=Rules!$B$11,Data!K11>=Rules!$B$12),"PASS","FAIL"),"FAIL") -> PASS | K11: =IF(AND(ISNUMBER(Data!W11),ISNUMBER(Data!X11)),IF(AND(Data!W11<=Rules!$B$13,Data!X11<=Rules!$B$14),"PASS","FAIL"),"FAIL") -> PASS | L11: =IF(F11="FAIL","רווחיות; ","")&IF(G11="FAIL","תזרים; ","")&IF(H11="FAIL","תשואה על ההון; ","")&IF(I11="FAIL","מאזן; ","")&IF(J11="FAIL","צמיחה; ","")&IF(K11="FAIL","דילול; ","") | M11: HIGH | N11: =IF(M11="EXTREME",Rules!$B$23,IF(M11="HIGH",Rules!$B$22,Rules!$B$21)) -> 0.06 | O11: 87.224825 | P11: Q4 | Q11: לא | R11: =IF(Q11="כן",P11,"לא רלוונטי (SMA200 יורד)") -> לא רלוונטי (SMA200 יורד) | S11: =IF(NOT(ISNUMBER(T11)),"n/a",IF(AND(T11>Rules!$B$18,ISNUMBER(U11),U11<Rules!$B$19),"יקרה",IF(T11<Rules!$B$20,"זולה","הוגנת"))) -> זולה | T11: =Data!AA11 -> 0.5847194 | U11: =Data!AC11 -> 0.07795292 | V11: 0.0328 | W11: -0.3952
A12: =Data!A12 -> BSX | B12: =Data!B12 -> Boston Scientific Corp. | C12: =Data!F12 -> STD | D12: =IF(E12=0,"CORE",IF(E12=1,"WATCH","NON-CORE")) -> CORE | E12: =COUNTIF(F12:K12,"FAIL") -> 0 | F12: =IF(C12="FIN",IF(Data!M12=Data!H12,"PASS","FAIL"),IF(AND(ISNUMBER(Data!L12),Data!L12>=Rules!$B$5,IF(Data!H12<5,Data!M12=Data!H12,Data!M12>=Rules!$B$6)),"PASS","FAIL")) -> PASS | G12: =IF(C12="FIN","n/a",IF(C12="UTIL/REIT",IF(Data!Q12=Data!H12,"PASS","FAIL"),IF(AND(ISNUMBER(Data!N12),Data!N12>0,IF(Data!H12<5,Data!P12=Data!H12,Data!P12>=Rules!$B$7)),"PASS","FAIL"))) -> PASS | H12: =IF(C12="FIN",IF(AND(ISNUMBER(Data!S12),Data!S12>=Rules!$B$15),"PASS","FAIL"),IF(AND(ISNUMBER(Data!R12),Data!R12>=Rules!$B$8),"PASS","FAIL")) -> PASS | I12: =IF(C12="FIN","n/a",IF(C12="UTIL/REIT",IF(AND(Data!U12<=Rules!$B$16,Data!V12>=Rules!$B$17),"PASS","FAIL"),IF(AND(Data!U12<=Rules!$B$9,Data!V12>=Rules!$B$10),"PASS","FAIL"))) -> PASS | J12: =IF(AND(ISNUMBER(Data!J12),ISNUMBER(Data!K12)),IF(AND(Data!J12>=Rules!$B$11,Data!K12>=Rules!$B$12),"PASS","FAIL"),"FAIL") -> PASS | K12: =IF(AND(ISNUMBER(Data!W12),ISNUMBER(Data!X12)),IF(AND(Data!W12<=Rules!$B$13,Data!X12<=Rules!$B$14),"PASS","FAIL"),"FAIL") -> PASS | L12: =IF(F12="FAIL","רווחיות; ","")&IF(G12="FAIL","תזרים; ","")&IF(H12="FAIL","תשואה על ההון; ","")&IF(I12="FAIL","מאזן; ","")&IF(J12="FAIL","צמיחה; ","")&IF(K12="FAIL","דילול; ","") | M12: HIGH | N12: =IF(M12="EXTREME",Rules!$B$23,IF(M12="HIGH",Rules!$B$22,Rules!$B$21)) -> 0.06 | O12: 93.817662 | P12: Q4 | Q12: לא | R12: =IF(Q12="כן",P12,"לא רלוונטי (SMA200 יורד)") -> לא רלוונטי (SMA200 יורד) | S12: =IF(NOT(ISNUMBER(T12)),"n/a",IF(AND(T12>Rules!$B$18,ISNUMBER(U12),U12<Rules!$B$19),"יקרה",IF(T12<Rules!$B$20,"זולה","הוגנת"))) -> זולה | T12: =Data!AA12 -> 0.28268485 | U12: =Data!AC12 -> 0.056710704 | V12: 0.0312 | W12: -0.6058
A13: =Data!A13 -> CAT | B13: =Data!B13 -> Caterpillar Inc. | C13: =Data!F13 -> STD | D13: =IF(E13=0,"CORE",IF(E13=1,"WATCH","NON-CORE")) -> CORE | E13: =COUNTIF(F13:K13,"FAIL") -> 0 | F13: =IF(C13="FIN",IF(Data!M13=Data!H13,"PASS","FAIL"),IF(AND(ISNUMBER(Data!L13),Data!L13>=Rules!$B$5,IF(Data!H13<5,Data!M13=Data!H13,Data!M13>=Rules!$B$6)),"PASS","FAIL")) -> PASS | G13: =IF(C13="FIN","n/a",IF(C13="UTIL/REIT",IF(Data!Q13=Data!H13,"PASS","FAIL"),IF(AND(ISNUMBER(Data!N13),Data!N13>0,IF(Data!H13<5,Data!P13=Data!H13,Data!P13>=Rules!$B$7)),"PASS","FAIL"))) -> PASS | H13: =IF(C13="FIN",IF(AND(ISNUMBER(Data!S13),Data!S13>=Rules!$B$15),"PASS","FAIL"),IF(AND(ISNUMBER(Data!R13),Data!R13>=Rules!$B$8),"PASS","FAIL")) -> PASS | I13: =IF(C13="FIN","n/a",IF(C13="UTIL/REIT",IF(AND(Data!U13<=Rules!$B$16,Data!V13>=Rules!$B$17),"PASS","FAIL"),IF(AND(Data!U13<=Rules!$B$9,Data!V13>=Rules!$B$10),"PASS","FAIL"))) -> PASS | J13: =IF(AND(ISNUMBER(Data!J13),ISNUMBER(Data!K13)),IF(AND(Data!J13>=Rules!$B$11,Data!K13>=Rules!$B$12),"PASS","FAIL"),"FAIL") -> PASS | K13: =IF(AND(ISNUMBER(Data!W13),ISNUMBER(Data!X13)),IF(AND(Data!W13<=Rules!$B$13,Data!X13<=Rules!$B$14),"PASS","FAIL"),"FAIL") -> PASS | L13: =IF(F13="FAIL","רווחיות; ","")&IF(G13="FAIL","תזרים; ","")&IF(H13="FAIL","תשואה על ההון; ","")&IF(I13="FAIL","מאזן; ","")&IF(J13="FAIL","צמיחה; ","")&IF(K13="FAIL","דילול; ","") | M13: HIGH | N13: =IF(M13="EXTREME",Rules!$B$23,IF(M13="HIGH",Rules!$B$22,Rules!$B$21)) -> 0.06 | O13: 88.302667 | P13: Q4 | Q13: כן | R13: =IF(Q13="כן",P13,"לא רלוונטי (SMA200 יורד)") -> Q4 | S13: =IF(NOT(ISNUMBER(T13)),"n/a",IF(AND(T13>Rules!$B$18,ISNUMBER(U13),U13<Rules!$B$19),"יקרה",IF(T13<Rules!$B$20,"זולה","הוגנת"))) -> הוגנת | T13: =Data!AA13 -> 1.9175279 | U13: =Data!AC13 -> 0.024872785 | V13: 0.0302 | W13: -0.3428
... A121: =Data!A121 -> XOM | B121: =Data!B121 -> ExxonMobil Holdings Corp. | C121: =Data!F121 -> STD | D121: =IF(E121=0,"CORE",IF(E121=1,"WATCH","NON-CORE")) -> NON-CORE | E121: =COUNTIF(F121:K121,"FAIL") -> 2 | F121: =IF(C121="FIN",IF(Data!M121=Data!H121,"PASS","FAIL"),IF(AND(ISNUMBER(Data!L121),Data!L121>=Rules!$B$5,IF(Data!H121<5,Data!M121=Data!H121,Data!M121>=Rules!$B$6)),"PASS","FAIL")) -> PASS | G121: =IF(C121="FIN","n/a",IF(C121="UTIL/REIT",IF(Data!Q121=Data!H121,"PASS","FAIL"),IF(AND(ISNUMBER(Data!N121),Data!N121>0,IF(Data!H121<5,Data!P121=Data!H121,Data!P121>=Rules!$B$7)),"PASS","FAIL"))) -> PASS | H121: =IF(C121="FIN",IF(AND(ISNUMBER(Data!S121),Data!S121>=Rules!$B$15),"PASS","FAIL"),IF(AND(ISNUMBER(Data!R121),Data!R121>=Rules!$B$8),"PASS","FAIL")) -> FAIL | I121: =IF(C121="FIN","n/a",IF(C121="UTIL/REIT",IF(AND(Data!U121<=Rules!$B$16,Data!V121>=Rules!$B$17),"PASS","FAIL"),IF(AND(Data!U121<=Rules!$B$9,Data!V121>=Rules!$B$10),"PASS","FAIL"))) -> PASS | J121: =IF(AND(ISNUMBER(Data!J121),ISNUMBER(Data!K121)),IF(AND(Data!J121>=Rules!$B$11,Data!K121>=Rules!$B$12),"PASS","FAIL"),"FAIL") -> FAIL | K121: =IF(AND(ISNUMBER(Data!W121),ISNUMBER(Data!X121)),IF(AND(Data!W121<=Rules!$B$13,Data!X121<=Rules!$B$14),"PASS","FAIL"),"FAIL") -> PASS | L121: =IF(F121="FAIL","רווחיות; ","")&IF(G121="FAIL","תזרים; ","")&IF(H121="FAIL","תשואה על ההון; ","")&IF(I121="FAIL","מאזן; ","")&IF(J121="FAIL","צמיחה; ","")&IF(K121="FAIL","דילול; ","") -> תשואה על ההון; צמיחה; | M121: MEDIUM | N121: =IF(M121="EXTREME",Rules!$B$23,IF(M121="HIGH",Rules!$B$22,Rules!$B$21)) -> 0.1 | O121: 32.552552 | P121: Q2 | Q121: כן | R121: =IF(Q121="כן",P121,"לא רלוונטי (SMA200 יורד)") -> Q2 | S121: =IF(NOT(ISNUMBER(T121)),"n/a",IF(AND(T121>Rules!$B$18,ISNUMBER(U121),U121<Rules!$B$19),"יקרה",IF(T121<Rules!$B$20,"זולה","הוגנת"))) -> הוגנת | T121: =Data!AA121 -> 1.9698679 | U121: =Data!AC121 -> 0.042559882 | V121: 0.0199 | W121: -0.2068
A123: תווית ושווי מחושבים בנוסחאות מגיליונות Data ו־Rules. Cheap Score, Risk Tier, ADR60 ו־Max DD מה־DB שלנו נכון ל־30.9.2026. התווית היא סינון מכני בלבד — WATCH דורש קריאה של הסיבה; גם CORE לא בוחן חפיר תחרותי, הנהלה או תחזיות.

Sheet Rules
A1: כללי סינון CORE — הוקפאו 13.10.2026 לפני ניקוד החברות
A2: ספים (כחול = קלט). שינוי ספים משנה את התוויות ברשימה — לשימוש "מה אם" בלבד; הכללים הרשמיים הם הערכים האלה.
A4: סף | B4: ערך
A5: שולי רווח תפעולי מינימליים (STD, UTIL) | B5: 0.1
A6: מספר שנים מינימלי עם רווח נקי חיובי מתוך 5 | B6: 4
A7: מספר שנים מינימלי עם FCF חיובי מתוך 5 | B7: 4
A8: ROIC מינימלי (STD, UTIL) | B8: 0.1
A9: חוב נטו / EBITDA מקסימלי (STD) | B9: 3
A10: כיסוי ריבית מינימלי (STD) | B10: 5
A11: צמיחת הכנסות שנתית ממוצעת 3 שנים מינימלית | B11: 0.03
A12: ירידת הכנסות מקסימלית בשנה האחרונה | B12: -0.05
A13: גידול מקסימלי במספר המניות ב־3 שנים (דילול) | B13: 0.05
A14: תגמול במניות / הכנסות מקסימלי | B14: 0.15
A15: ROE מינימלי (FIN) | B15: 0.1
A16: חוב נטו / EBITDA מקסימלי (UTIL/REIT) | B16: 6
... A23: תקרת פוזיציית CORE — EXTREME | B23: 0.03
A25: מחלקות: FIN = בנקים, ברוקרים, ביטוח, מנהלי נכסים, בורסת קריפטו (JPM BAC WFC C GS MS SCHW SOFI HOOD AXP CB PGR BRK-B BLK BX KKR COIN). UTIL/REIT = DUK SO NEE PLD AMT. STD = כל השאר.
A26: 1. רווחיות — STD/UTIL: שולי רווח תפעולי בשנה האחרונה ≥ הסף, ורווח נקי חיובי ב־4 מתוך 5 שנים (בכל השנים אם יש פחות מ־5). FIN: רווח נקי חיובי בכל השנים.
A27: 2. תזרים — STD: FCF חיובי בשנה האחרונה וב־4 מתוך 5 שנים. UTIL/REIT: תזרים מפעילות חיובי בכל השנים (ההשקעות שלהן גדולות במבנה). FIN: לא רלוונטי.
A28: 3. תשואה על ההון — STD/UTIL: ROIC = הגבוה מבין ROIC של הספק (TTM) לבין רווח תפעולי × 0.79 / (חוב + הון − מזומן). FIN: רווח נקי / הון.
A29: 4. מאזן — STD: חוב נטו / EBITDA ≤ 3 (מזומן נטו עובר) וכיסוי ריבית ≥ 5. UTIL/REIT: ≤ 6 ו־≥ 2. FIN: לא רלוונטי.
A30: 5. צמיחה — צמיחת הכנסות שנתית ממוצעת ב־3 השנים האחרונות ≥ 3%, וההכנסות בשנה האחרונה לא ירדו ביותר מ־5%.
A31: 6. דילול — מספר המניות לא גדל ביותר מ־5% ב־3 שנים, ותגמול במניות ≤ 15% מההכנסות.
A32: תווית: CORE = עברה את כל 6. WATCH = נכשלה באחד — דורשת קריאה אנושית של הסיבה לפני שתהיה CORE. NON-CORE = נכשלה ב־2 ומעלה.
A33: שווי (מידע בלבד, לא משנה את התווית): P/E נוכחי חלקי החציון של ה־P/E השנתי של החברה עצמה.
A34: Cheap Score (מה־DB שלנו, נכון ל־30.9.2026): לפי NEW_PROTOCOL. נבדק היסטורית רק כש־SMA200 עולה; כשהוא יורד — מחוץ לתנאי הבדיקה, ולכן מסומן "לא רלוונטי".
A35: מגבלות: הספים לא נבדקו היסטורית (אין נתוני דוחות point-in-time) — זה מסנן איכות, לא טענה ל־edge. תחזיות אנליסטים לרוב על בסיס מותאם (לא GAAP) ולכן מוצגות בלבד. TSM בדולר טייוואני ו־ASML באירו — היחסים לא מושפעים. סף שולי רווח 10% מפיל עסקים עם שוליים נמוכים מטבעם (COST, WMT, ביטוח בריאות) — לכן הם WATCH ולא NON-CORE אוטומטית.
A36: מקור הנתונים: Bigdata.com (https://bigdata.com), ספק FMP, דוחות שנתיים, נשלף 13.10.2026. סיכון ותקרות: risk_engine.csv מה־DB שלנו (5 שנים).

Sheet Data
A1: סימול | B1: שם | C1: סקטור | D1: תעשייה | E1: מטבע | F1: מחלקה | G1: סוף שנת הדוח האחרונה | H1: שנים בנתונים | I1: הכנסות שנה אחרונה (מיליון) | J1: צמיחת הכנסות שנתית 3 שנים | K1: שינוי הכנסות שנה אחרונה | L1: שולי רווח תפעולי | M1: שנים עם רווח נקי חיובי | N1: FCF שנה אחרונה (מיליון) | O1: שולי FCF | P1: שנים עם FCF חיובי | Q1: שנים עם תזרים מפעילות חיובי | R1: ROIC | S1: ROE שנה אחרונה | T1: חוב נטו (מיליון) | U1: חוב נטו / EBITDA | V1: כיסוי ריבית | W1: שינוי במספר המניות 3 שנים | X1: תגמול במניות / הכנסות | Y1: P/E נוכחי (TTM) | Z1: חציון P/E שנתי של החברה | AA1: P/E נוכחי / חציון עצמי | AB1: EV/EBITDA נוכחי | AC1: FCF yield נוכחי | AD1: צמיחת הכנסות צפויה (אנליסטים, מידע בלבד) | AE1: הערות על הנתונים
A2: ABNB | B2: Airbnb Inc. | C2: Consumer Services | D2: Travel and Tourism | E2: USD | F2: STD | G2: 2025-12-31 | H2: 5 | I2: 12305 | J2: 0.13575506 | K2: 0.10835885 | L2: 0.21202763 | M2: 4 | N2: 4646 | O2: 0.37757009 | P2: 5 | Q2: 5 | R2: 0.20689878 | S2: 0.30625686 | T2: -8743 | U2: -3.2381481 | V2: 999 | W2: -0.083823529 | X2: 0.1293783 | Y2: 37.129955 | Z2: 30.075324 | AA2: =IF(AND(ISNUMBER(Y2),ISNUMBER(Z2),Y2>0,Z2>0),Y2/Z2,"") -> 1.2345654 | AB2: 30.89251 | AC2: 0.049967079 | AD2: 0.15243471 | AE2: Cash includes customer funds per source (cash_and_short_term_investments 11014000000). FY2023 net_income includes tax benefit (income_tax -2690000000). FY2025 net_income field is 2511000000 (bottom_line_net_income 2514000000). FY2026+ are estimates. capex 0 and interest_expense 0 as returned for FY2024/FY2025.
A3: ADBE | B3: Adobe Inc. | C3: Technology | D3: Software | E3: USD | F3: STD | G3: 2025-11-28 | H3: 5 | I3: 23769 | J3: 0.1052234 | K3: 0.10527784 | L3: 0.3662754 | M3: 5 | N3: 9852 | O3: 0.41448946 | P3: 5 | Q3: 5 | R3: 0.58904933 | S3: 0.61343887 | T3: 53 | U3: 0.0053998981 | V3: 33.102662 | W3: -0.093418259 | X3: 0.081703059 | Y3: 13.222067 | Z3: 41.473473 | AA3: =IF(AND(ISNUMBER(Y3),ISNUMBER(Z3),Y3>0,Z3>0),Y3/Z3,"") -> 0.31880781 | AB3: 9.4495116 | AC3: 0.11595158 | AD3: 0.11955212 | AE3: Fiscal year ends November (report dates late Nov/early Dec). No dividends.
A4: ADP | B4: Automatic Data Processing Inc. | C4: Industrials | D4: Financial Administration | E4: USD | F4: STD | G4: 2026-06-30 | H4: 5 | I4: 21947.5 | J4: 0.068085696 | K4: 0.067438682 | L4: 0.18582526 | M4: 5 | N4: 5244.6 | O4: 0.23896116 | P4: 5 | Q4: 5 | R4: 0.45559694 | S4: 0.73177809 | T4: 1040.7 | U4: 0.16138887 | V4: 8.8815331 | W4: -0.039141208 | X4: 0.011053651 | Y4: 25.116682 | Z4: 26.641212 | AA4: =IF(AND(ISNUMBER(Y4),ISNUMBER(Z4),Y4>0,Z4>0),Y4/Z4,"") -> 0.94277549 | AB4: 17.241395 | AC4: 0.045209355 | AD4: 0.057673829 | AE4: Fiscal year ends June 30. FY2026 operating_income (4078400000) is below ebit (5862500000) as returned. FY2026 balance sheet: other_non_current_assets 48622400000 and total_current_assets 8603300000; TTM current_ratio 0.172 vs FY2025 1.048 as returned. Total assets include large other_current_assets in earlier years. TTM and FY2026 key_metrics differ (TTM pe 25.1 vs FY 20.4) as returned. Provider FMP.
A5: ANET | B5: Arista Networks Inc. | C5: Technology | D5: Internet Services | E5: USD | F5: STD | G5: 2025-12-31 | H5: 5 | I5: 9005.7 | J5: 0.27146526 | K5: 0.28595908 | L5: 0.42818437 | M5: 5 | N5: 4252.4 | O5: 0.47218984 | P5: 5 | Q5: 5 | R5: 1.8717782 | S5: 0.28385271 | T5: -10743 | U5: -2.4854823 | V5: 999 | W5: 0.0077932748 | X5: 0.048769113 | Y5: 65.694704 | Z5: 46.964158 | AA5: =IF(AND(ISNUMBER(Y5),ISNUMBER(Z5),Y5>0,Z5>0),Y5/Z5,"") -> 1.3988264 | AB5: 51.790012 | AC5: 0.019414865 | AD5: 0.40848228 | AE5: No debt (total_debt 0, interest_expense 0, interest_coverage 0). Share/EPS data split-adjusted as returned. TTM key metrics (pe 65.7, ev_to_ebitda 51.8) differ from FY2025 (47.0, 37.7).
A6: APH | B6: Amphenol Corp. | C6: Industrials | D6: Electrical Components and Equipment | E6: USD | F6: STD | G6: 2025-12-31 | H6: 5 | I6: 23094.7 | J6: 0.22306606 | K6: 0.51712246 | L6: 0.25411025 | M6: 5 | N6: 4378.1 | O6: 0.18957163 | P6: 5 | Q6: 5 | R6: 0.2637573 | S6: 0.3160914 | T6: 4067.8 | U6: 0.58354852 | V6: 15.955954 | W6: 0.028582931 | X6: 0 | Y6: 40.442857 | Z6: 32.887218 | AA6: =IF(AND(ISNUMBER(Y6),ISNUMBER(Z6),Y6>0,Z6>0),Y6/Z6,"") -> 1.2297439 | AB6: 24.566977 | AC6: 0.022177829 | AD6: 0.54057372 | AE6: stock_based_compensation FY2025 returned 0. total_equity includes minority_interest (FY2025 stockholders equity 13413100000). FY2026+ are estimates.
A7: APP | B7: AppLovin Corp. | C7: Consumer Services | D7: Media Agencies | E7: USD | F7: STD | G7: 2025-12-31 | H7: 5 | I7: 5480.717 | J7: 0.24838113 | K7: 0.69994367 | L7: 0.75754942 | M7: 4 | N7: 3942.776 | O7: 0.71939055 | P7: 5 | Q7: 5 | R7: 1.027471 | S7: 1.5617226 | T7: 1057.645 | U7: 0.24287414 | V7: 20.056005 | W7: -0.079657048 | X7: 0.038392969 | Y7: 20.72456 | Z7: 68.836043 | AA7: =IF(AND(ISNUMBER(Y7),ISNUMBER(Z7),Y7>0,Z7>0),Y7/Z7,"") -> 0.30107134 | AB7: 16.477873 | AC7: 0.049444747 | AD7: 0.48208055 | AE7: FY2021 eps_diluted returned as 0.093. FY2021 total_equity uses total_equity 2138291000 (stockholders equity 2138090000). TTM market data (pe 20.7, EV 91.5B) appears inconsistent with FY2025 year-end valuation (pe 68.5, EV 229B); copied as returned.
A8: ASML | B8: ASML Holding N.V. | E8: EUR | F8: STD | G8: 2025-12-31 | H8: 5 | I8: 32667.3 | J8: 0.15551134 | K8: 0.1558368 | L8: 0.34595452 | M8: 5 | N8: 11084.9 | O8: 0.33932709 | P8: 5 | Q8: 5 | R8: 0.83587106 | S8: 0.48997053 | T8: -8931 | U8: -0.71838803 | V8: 999 | W8: -0.022864322 | X8: 0 | Y8: 55.428156 | Z8: 36.087904 | AA8: =IF(AND(ISNUMBER(Y8),ISNUMBER(Z8),Y8>0,Z8>0),Y8/Z8,"") -> 1.5359206 | AB8: 42.310624 | AC8: 0.016987946 | AD8: 0.34852415 | AE8: FOREIGN: all figures in EUR. Sector and industry not returned by tearsheet (null). FY ends Dec. FY2025 interest_expense 0 and stock_based_compensation 0 as returned; TTM interest_coverage 0 as returned. Cash-flow net income FY2022 6395800000 differs from income-statement net_income 5624200000.
A9: AXP | B9: American Express Co. | C9: Financials | D9: Consumer Finance | E9: USD | F9: FIN | G9: 2025-12-31 | H9: 5 | I9: 80464 | J9: 0.1309512 | K9: 0.084405871 | L9: 0.17144313 | M9: 5 | N9: 16003 | O9: 0.19888397 | P9: 5 | Q9: 5 | R9: 0.25522963 | S9: 0.32362431 | T9: 9225 | U9: 0.59240945 | V9: 1.6753704 | W9: -0.074468085 | X9: 0.0068477829 | Y9: 18.892056 | Z9: 16.682102 | AA9: =IF(AND(ISNUMBER(Y9),ISNUMBER(Z9),Y9>0,Z9>0),Y9/Z9,"") -> 1.1324746 | AB9: 8.9926782 | AC9: 0.072181816 | AD9: -0.012327052 | AE9: Financial/consumer-finance format (negative working capital, interest expense large). TTM current_ratio 1.55 vs FY ~0.28. FY2021 gross_profit exceeds revenue (cost_of_revenue negative). SALES 2030 estimate (76.4B) lower than 2029 - copied as returned but not included (only first two years).
A10: BAC | B10: Bank of America Corp. | C10: Financials | D10: Diversified Banks | E10: USD | F10: FIN | G10: 2025-12-31 | H10: 5 | I10: 191567 | J10: 0.1852435 | K10: -0.0045054408 | L10: 0.19677189 | M10: 5 | N10: 12613 | O10: 0.065841194 | P10: 2 | Q10: 2 | R10: 0.0096185834 | S10: 0.10060908 | T10: -597828 | U10: -14.942338 | V10: 0.48037467 | W10: -0.075984083 | X10: 0.020885643 | Y10: 12.329932 | Z10: 12.358333 | AA10: =IF(AND(ISNUMBER(Y10),ISNUMBER(Z10),Y10>0,Z10>0),Y10/Z10,"") -> 0.99770185 | AB10: 23.550256 | AC10: 0.24552378 | AD10: -0.3557528 | AE10: Bank format: capex 0, operating cash flow and FCF volatile/not meaningful (FCF-based multiples meaningless), TTM current_ratio 0.07, interest_coverage <1, TTM ROIC equals ROA. FY2021 gross_profit exceeds revenue (small cost_of_revenue). Estimated SALES (123B for 2026) on a different basis than reported FY2025 revenue (191.6B).
A11: BKNG | B11: Booking Holdings Inc. | C11: Consumer Services | D11: Travel and Tourism | E11: USD | F11: STD | G11: 2025-12-31 | H11: 5 | I11: 26917 | J11: 0.16348699 | K11: 0.13387253 | L11: 0.34483783 | M11: 5 | N11: 9087 | O11: 0.33759334 | P11: 5 | Q11: 5 | R11: 0.71229483 | T11: 1508 | U11: 0.16361072 | V11: 5.7402597 | W11: -0.18508439 | X11: 0.022922317 | Y11: 17.478267 | Z11: 29.891717 | AA11: =IF(AND(ISNUMBER(Y11),ISNUMBER(Z11),Y11>0,Z11>0),Y11/Z11,"") -> 0.5847194 | AB11: 11.666704 | AC11: 0.07795292 | AD11: 0.086761577 | AE11: NEGATIVE EQUITY: total_equity -5578000000 (FY2025), -4020000000 (FY2024), -2744000000 (FY2023); price_to_book, return_on_equity and debt_to_equity are negative in source. cost_of_revenue 0 so gross_profit equals revenue. ttm pe_ratio 17.48 vs FY2025 fy_pe_ratio 32.16 copied as returned (not reconciled). FY2026+ are estimates.
A12: BSX | B12: Boston Scientific Corp. | C12: Health Care | D12: Medical Equipment | E12: USD | F12: STD | G12: 2025-12-31 | H12: 5 | I12: 20074 | J12: 0.1654189 | K12: 0.19866245 | L12: 0.19781807 | M12: 5 | N12: 3658 | O12: 0.18222576 | P12: 5 | Q12: 5 | R12: 0.10570818 | S12: 0.1179307 | T12: 10373 | U12: 2.0331243 | V12: 11.378223 | W12: 0.038063485 | X12: 0.014894889 | Y12: 17.340726 | Z12: 61.34296 | AA12: =IF(AND(ISNUMBER(Y12),ISNUMBER(Z12),Y12>0,Z12>0),Y12/Z12,"") -> 0.28268485 | AB12: 13.097693 | AC12: 0.056710704 | AD12: 0.056587788 | AE12: total_equity includes minority_interest (FY2025 stockholders equity 24233000000). FY2022 common_stock_repurchased is +136000000 as returned. Source ttm pe_ratio 17.34 and FY2025 fy_pe_ratio 48.65 copied as returned (they differ widely; not reconciled). FY2026+ are estimates.
A13: CAT | B13: Caterpillar Inc. | C13: Industrials | D13: Commercial Vehicles and Trucks | E13: USD | F13: STD | G13: 2025-12-31 | H13: 5 | I13: 67589 | J13: 0.043832316 | K13: 0.042895277 | L13: 0.16585539 | M13: 5 | N13: 7453 | O13: 0.11026942 | P13: 5 | Q13: 5 | R13: 0.16199422 | S13: 0.41622103 | T13: 33350 | U13: 2.2450353 | V13: 10.883495 | W13: -0.11576169 | X13: 0.0035804643 | Y13: 33.229649 | Z13: 17.329422 | AA13: =IF(AND(ISNUMBER(Y13),ISNUMBER(Z13),Y13>0,Z13>0),Y13/Z13,"") -> 1.9175279 | AB13: 22.987763 | AC13: 0.024872785 | AD13: 0.17763129 | AE13: Consolidated incl. Financial Products (total_debt includes financial-services debt, net_debt_to_ebitda/debt_to_equity reflect that). total_equity includes minority_interest (tiny). FY2026+ are estimates.
A14: CB | B14: Chubb Ltd. | C14: Financials | D14: Property and Casualty Insurance | E14: USD | F14: FIN | G14: 2025-12-31 | H14: 5 | I14: 59783 | J14: 0.11631632 | K14: 0.064701692 | L14: 0.21818912 | M14: 5 | N14: 14537 | O14: 0.24316277 | P14: 5 | Q14: 5 | R14: 0.18789563 | S14: 0.129232 | T14: -24936 | U14: -1.7673825 | V14: 17.073298 | W14: -0.063814113 | X14: 0 | Y14: 12.17428 | Z14: 12.044464 | AA14: =IF(AND(ISNUMBER(Y14),ISNUMBER(Z14),Y14>0,Z14>0),Y14/Z14,"") -> 1.0107781 | AB14: 12.224919 | AC14: 0.12027202 | AD14: -0.013200377 | AE14: Insurance format: capex 0 and free_cash_flow equals operating_cash_flow as returned; cash_and_short_term_investments includes short-term investments; FY2021 cash_and_short_term_investments 97913000000 as returned. FY2024 shares_diluted 411905820 as returned (income stmt).
A15: CME | B15: CME Group Inc. | C15: Financials | D15: Investment Services | E15: USD | F15: STD | G15: 2025-12-31 | H15: 5 | I15: 6520.6 | J15: 0.091135245 | K15: 0.06370206 | L15: 0.64863663 | M15: 5 | N15: 4193.6 | O15: 0.643131 | P15: 5 | Q15: 5 | R15: 0.12102406 | S15: 0.14078153 | T15: -1119.6 | U15: -0.19382985 | V15: 32.609869 | W15: 0.0029288854 | X15: 0.014538539 | Y15: 23.395781 | Z15: 23.965944 | AA15: =IF(AND(ISNUMBER(Y15),ISNUMBER(Z15),Y15>0,Z15>0),Y15/Z15,"") -> 0.97620942 | AB15: 18.33113 | AC15: 0.042059365 | AD15: 0.081167463 | AE15: Exchange operator; balance sheet includes large clearing-house/performance-bond items (other_current_assets ~160B, total_assets ~198B). Provider cash_end_of_period includes restricted/clearing cash (164B) so net_change_in_cash is large. Provider FMP.
A16: CRM | B16: Salesforce, Inc. | E16: USD | F16: STD | G16: 2026-01-31 | H16: 5 | I16: 41525 | J16: 0.098200061 | K16: 0.095791001 | L16: 0.21473811 | M16: 5 | N16: 14402 | O16: 0.34682721 | P16: 5 | Q16: 5 | R16: 0.10552979 | S16: 0.12608637 | T16: 7611 | U16: 0.57873926 | V16: 27.521605 | W16: -0.04112337 | X16: 0.084503311 | Y16: 21.703955 | Z16: 66.138824 | AA16: =IF(AND(ISNUMBER(Y16),ISNUMBER(Z16),Y16>0,Z16>0),Y16/Z16,"") -> 0.32815755 | AB16: 13.655629 | AC16: 0.077501806 | AD16: 0.11468764 | AE16: Fiscal year ends January; source fiscal_year N has report_date N-01-31 (fiscal_year 2026 = FYE 2026-01-31). Estimates are for fiscal_year 2027 (FYE 2027-01-31) and 2028 as returned, since fiscal_year 2026 is already reported. sector and industry not returned by the requested sections. Ttm and FY values copied as returned (fy_pe_ratio FY2023 799.857). FY2027+ are estimates.
A17: CSCO | B17: Cisco Systems Inc. | C17: Technology | D17: Computer Services | E17: USD | F17: STD | G17: 2026-07-25 | H17: 5 | I17: 63325 | J17: 0.035710853 | K17: 0.11774985 | L17: 0.24268456 | M17: 5 | N17: 12767 | O17: 0.20161074 | P17: 5 | Q17: 5 | R17: 0.18999562 | S17: 0.26383613 | T17: 13615 | U17: 0.6801039 | V17: 10.454422 | W17: -0.028745432 | X17: 0.060481642 | Y17: 34.025298 | Z17: 18.776471 | AA17: =IF(AND(ISNUMBER(Y17),ISNUMBER(Z17),Y17>0,Z17>0),Y17/Z17,"") -> 1.8121242 | AB17: 23.634159 | AC17: 0.030170581 | AD17: 0.15181287 | AE17: Fiscal year ends July; FY2026 (2026-07-25) already reported. Tearsheet source FMP.
A18: ETN | B18: Eaton Corp. PLC | C18: Industrials | D18: Diversified Industrials | E18: USD | F18: STD | G18: 2025-12-31 | H18: 5 | I18: 27448 | J18: 0.097699792 | K18: 0.10330412 | L18: 0.19050568 | M18: 5 | N18: 3553 | O18: 0.12944477 | P18: 5 | Q18: 5 | R18: 0.13845852 | S18: 0.2100262 | T18: 10366 | U18: 1.6713963 | V18: 19.806818 | W18: -0.028193613 | X18: 0.0018216263 | Y18: 43.274848 | Z18: 30.363203 | AA18: =IF(AND(ISNUMBER(Y18),ISNUMBER(Z18),Y18>0,Z18>0),Y18/Z18,"") -> 1.4252399 | AB18: 28.887522 | AC18: 0.027184323 | AD18: 0.20101368 | AE18: Irish-domiciled, reports in USD. find_securities with query ETN returned only private entities; resolved via query 'Eaton Corporation' (id C4073B, listing XNYS:ETN). stock_based_compensation FY2025 is -50000000 and 0 for FY2021-2024 as returned. total_equity includes minority_interest (FY2025 stockholders equity 19425000000). FY2026+ are estimates.
A19: GE | B19: GE Aerospace | C19: Industrials | D19: Diversified Industrials | E19: USD | F19: STD | G19: 2025-12-31 | H19: 5 | I19: 45855 | J19: 0.16315436 | K19: 0.18482249 | L19: 0.19125504 | M19: 4 | N19: 7264 | O19: 0.15841239 | P19: 5 | Q19: 5 | R19: 0.2566037 | S19: 0.46057784 | T19: 8102 | U19: 0.67164055 | V19: 10.403321 | W19: -0.026459854 | X19: 0 | Y19: 35.960094 | Z19: 32.681506 | AA19: =IF(AND(ISNUMBER(Y19),ISNUMBER(Z19),Y19>0,Z19>0),Y19/Z19,"") -> 1.1003193 | AB19: 26.28023 | AC19: 0.0263019 | AD19: 0.097224392 | AE19: Entity is GE Aerospace (post-spin history restated/mixed: FY2021-2023 include prior conglomerate basis, FY2021 net loss, FY2022 eps 0.043 and fy_pe_ratio 1212.79 as returned). FY2026 EPS estimate 7.92883 is below FY2025 EPS 8.16 as returned. Tearsheet source FMP.
A20: GOOGL | B20: Alphabet Inc. | C20: Technology | D20: Internet Services | E20: USD | F20: STD | G20: 2025-12-31 | H20: 5 | I20: 402836 | J20: 0.12511746 | K20: 0.15090081 | L20: 0.32063917 | M20: 5 | N20: 73266 | O20: 0.1818755 | P20: 5 | Q20: 5 | R20: 0.29346142 | S20: 0.31827869 | T20: -67552 | U20: -0.37383922 | V20: 175.49592 | W20: -0.07059807 | X20: 0.061943322 | Y20: 17.542949 | Z20: 24.131849 | AA20: =IF(AND(ISNUMBER(Y20),ISNUMBER(Z20),Y20>0,Z20>0),Y20/Z20,"") -> 0.72696249 | AB20: 13.257955 | AC20: 0.012479964 | AD20: 0.23705027 | AE20: Estimate EPS FY2027 (15.21734) is lower than FY2026 (20.59129) as returned. TTM net_margin 0.5477 and ttm pe 17.54 as returned (TTM includes large other income). Tearsheet source FMP.
A21: GS | B21: Goldman Sachs Group Inc. | C21: Financials | D21: Investment Services | E21: USD | F21: FIN | G21: 2025-12-31 | H21: 5 | I21: 125097 | J21: 0.22106901 | K21: -0.013842794 | L21: 0.17468045 | M21: 5 | N21: -47218 | O21: -0.3774511 | P21: 2 | Q21: 2 | R21: 108.84351 | S21: 0.13743879 | T21: -14993 | U21: -0.62382458 | V21: 0.3270572 | W21: -0.1130969 | X21: 0.02753863 | Y21: 16.797257 | Z21: 13.8918 | AA21: =IF(AND(ISNUMBER(Y21),ISNUMBER(Z21),Y21>0,Z21>0),Y21/Z21,"") -> 1.209149 | AB21: 10.350864 | AC21: -0.15741985 | AD21: -0.43368617 | AE21: Bank/broker format: OCF/FCF negative and not meaningful; debt/net debt ratios not meaningful. TTM block appears anomalous as returned (return_on_invested_capital 108.84, price_to_book 125.17, debt_to_equity 0.042, current_ratio 1.92, enterprise_value 263636507650, ttm book_value_per_share 0.409) and is inconsistent with FY2025 values. FY2025 revenue 125097000000 vs FY2026 SALES estimate 70844160598 (basis mismatch as returned). Tearsheet source FMP.
A22: INTU | B22: Intuit Inc. | C22: Technology | D22: Software | E22: USD | F22: STD | G22: 2026-07-31 | H22: 5 | I22: 21448 | J22: 0.14286999 | K22: 0.13897297 | L22: 0.28799888 | M22: 5 | N22: 8617 | O22: 0.4017624 | P22: 5 | Q22: 5 | R22: 0.24142037 | S22: 0.24041702 | T22: 1221 | U22: 0.17151285 | V22: 24.128906 | W22: -0.021201413 | X22: 0.095859754 | Y22: 18.511192 | Z22: 60.341981 | AA22: =IF(AND(ISNUMBER(Y22),ISNUMBER(Z22),Y22>0,Z22>0),Y22/Z22,"") -> 0.30677136 | AB22: 12.08232 | AC22: 0.10295152 | AD22: 0.091753967 | AE22: Fiscal year ends July; FY2026 (ended 2026-07-31) is the latest. TTM ratios equal FY2026 largely. FY2026 balance sheet shows additional_paid_in_capital 0 and treasury_stock 0 (format change). FY2026 market cap 87.2B vs FY2025 219.8B (large drop).
A23: ISRG | B23: Intuitive Surgical Inc. | C23: Health Care | D23: Medical Equipment | E23: USD | F23: STD | G23: 2025-12-31 | H23: 5 | I23: 10064.7 | J23: 0.17386717 | K23: 0.20505023 | L23: 0.29265651 | M23: 5 | N23: 2490.7 | O23: 0.24746888 | P23: 5 | Q23: 5 | R23: 0.18903498 | S23: 0.15918224 | T23: -5632.1 | U23: -1.4120847 | V23: 999 | W23: 0.0019337017 | X23: 0.078313313 | Y23: 47.754237 | Z23: 71.330645 | AA23: =IF(AND(ISNUMBER(Y23),ISNUMBER(Z23),Y23>0,Z23>0),Y23/Z23,"") -> 0.66947715 | AB23: 32.296135 | AC23: 0.021584134 | AD23: 0.1684715 | AE23: interest_expense returned as 0 (no meaningful debt); interest_coverage 0 in source. total_equity includes minority_interest (FY2025 stockholders equity 17824000000). FY2026+ are estimates.
A24: JNJ | B24: Johnson & Johnson Co. | C24: Health Care | D24: Pharmaceuticals | E24: USD | F24: STD | G24: 2025-12-28 | H24: 5 | I24: 94193 | J24: 0.05599285 | K24: 0.060481193 | L24: 0.27173994 | M24: 5 | N24: 19698 | O24: 0.20912382 | P24: 5 | Q24: 5 | R24: 0.18487625 | S24: 0.32870597 | T24: 27831 | U24: 0.67789551 | V24: 26.360453 | W24: -0.08802883 | X24: 0.014374741 | Y24: 28.760694 | Z24: 21.631778 | AA24: =IF(AND(ISNUMBER(Y24),ISNUMBER(Z24),Y24>0,Z24>0),Y24/Z24,"") -> 1.3295575 | AB24: 18.80106 | AC24: 0.030892527 | AD24: 0.075721073 | AE24: FY2023 net_income (35.153B) differs from net_income_from_continuing_operations (13.326B). FY2025 total_other_income_expenses_net = 6.985B; FY2024 = -5.462B. FY2022-2021 fiscal weeks end on Jan 1 / Jan 2 dates. FY2025 shares_diluted equals FY2024 value as returned (2429400000).
A25: JPM | B25: JPMorgan Chase & Co. | C25: Financials | D25: Diversified Banks | E25: USD | F25: FIN | G25: 2025-12-31 | H25: 5 | I25: 279745 | J25: 0.22061699 | K25: 0.033073722 | L25: 0.25950419 | M25: 5 | N25: -147782 | O25: -0.52827396 | P25: 3 | Q25: 3 | R25: 0.078828428 | S25: 0.15740071 | T25: -537369 | U25: -6.6002874 | V25: 0.74153711 | W25: -0.059360269 | X25: 0 | Y25: 14.092585 | Z25: 11.082645 | AA25: =IF(AND(ISNUMBER(Y25),ISNUMBER(Z25),Y25>0,Z25>0),Y25/Z25,"") -> 1.2715904 | AB25: 15.215874 | AC25: -0.18182341 | AD25: -0.2555095 | AE25: Bank format: capex 0, operating cash flow and FCF negative/not meaningful (FCF-based multiples and yields meaningless), current_ratio TTM 10.28 vs FY 0.52, interest_expense exceeds operating income (interest_coverage <1), SBC 0. FY2021 gross_profit exceeds revenue (negative cost_of_revenue). Estimated SALES (208B for 2026) is on a different revenue basis than reported FY2025 revenue (279.7B).
A26: KLAC | B26: KLA Corp. | C26: Technology | D26: Semiconductors | E26: USD | F26: STD | G26: 2026-06-30 | H26: 5 | I26: 13579.476 | J26: 0.08964649 | K26: 0.1170858 | L26: 0.41686292 | M26: 5 | N26: 3767.134 | O26: 0.2774138 | P26: 5 | Q26: 5 | R26: 0.58849094 | S26: 0.7607729 | T26: 1249.305 | U26: 0.20633442 | V26: 19.901491 | W26: -0.058984562 | X26: 0.022841161 | Y26: 50.02443 | Z26: 29.338356 | AA26: =IF(AND(ISNUMBER(Y26),ISNUMBER(Z26),Y26>0,Z26>0),Y26/Z26,"") -> 1.7050864 | AB26: 40.960436 | AC26: 0.015470544 | AD26: 0.33821263 | AE26: Fiscal year ends June. Name returned 'KLA Corp.' (ticker KLAC on XNAS). Split-style fractional EPS values returned (e.g. 3.037, 2.028). Large gap between FY2026 key metrics (pe 82.0, ev_to_ebitda 66.1) and TTM (pe 50.0, ev_to_ebitda 41.0); TTM and FY2026 financial statement ratios are nearly identical, so the difference is price-date basis. Total equity thin relative to buybacks (ROE 0.85).
A27: KO | B27: Coca-Cola Co. | C27: Consumer Goods | D27: Soft Drinks | E27: USD | F27: STD | G27: 2025-12-31 | H27: 5 | I27: 47941 | J27: 0.036890141 | K27: 0.018699135 | L27: 0.28706118 | M27: 5 | N27: 5296 | O27: 0.11046912 | P27: 5 | Q27: 5 | R27: 0.16078767 | S27: 0.382407 | T27: 33342 | U27: 1.782804 | V27: 8.3204353 | W27: -0.0085057471 | X27: 0.0058196533 | Y27: 26.963964 | Z27: 25.206478 | AA27: =IF(AND(ISNUMBER(Y27),ISNUMBER(Z27),Y27>0,Z27>0),Y27/Z27,"") -> 1.0697236 | AB27: 21.025761 | AC27: 0.037007618 | AD27: 0.038806306
A28: LLY | B28: Eli Lilly & Co. | C28: Health Care | D28: Pharmaceuticals | E28: USD | F28: STD | G28: 2025-12-31 | H28: 5 | I28: 65179 | J28: 0.31687375 | K28: 0.4470395 | L28: 0.45560687 | M28: 5 | N28: 8972 | O28: 0.1376517 | P28: 4 | Q28: 5 | R28: 0.37979343 | S28: 0.77784059 | T28: 35235 | U28: 1.1117597 | V28: 37.339369 | W28: -0.054915795 | X28: 0.0096043204 | Y28: 39.28103 | Z28: 55.683409 | AA28: =IF(AND(ISNUMBER(Y28),ISNUMBER(Z28),Y28>0,Z28>0),Y28/Z28,"") -> 0.70543508 | AB28: 26.637113 | AC28: 0.018107411 | AD28: 0.36094005 | AE28: FY2026 and later are estimates; 5 fiscal years returned. Tearsheet also returned FY2028-2030 estimates (not copied).
A29: LMT | B29: Lockheed Martin Corp. | C29: Industrials | D29: Defense | E29: USD | F29: STD | G29: 2025-12-31 | H29: 5 | I29: 75057 | J29: 0.043880667 | K29: 0.056500992 | L29: 0.10300172 | M29: 5 | N29: 6908 | O29: 0.092036719 | P29: 5 | Q29: 5 | R29: 0.25133704 | S29: 0.7464663 | T29: 17579 | U29: 2.0143234 | V29: 6.9150268 | W29: -0.12358277 | X29: 0.0040502551 | Y29: 18.559622 | Z29: 21.703439 | AA29: =IF(AND(ISNUMBER(Y29),ISNUMBER(Z29),Y29>0,Z29>0),Y29/Z29,"") -> 0.8551466 | AB29: 13.009076 | AC29: 0.074815245 | AD29: 0.078599455 | AE29: Calendar fiscal year. Provider classifies industry as Defense. Operating_income (FY2025 7731000000) exceeds gross_profit (7619000000) as returned. Provider FMP.
A30: LRCX | B30: Lam Research Corp. | C30: Technology | D30: Semiconductors | E30: USD | F30: STD | G30: 2026-06-28 | H30: 5 | I30: 23232.69 | J30: 0.10059634 | K30: 0.26020858 | L30: 0.35294213 | M30: 5 | N30: 4891.252 | O30: 0.21053318 | P30: 5 | Q30: 5 | R30: 0.5881824 | S30: 0.58258696 | T30: -1457.606 | U30: -0.16746381 | V30: 999 | W30: -0.071585906 | X30: 0.01663092 | Y30: 53.464594 | Z30: 23.342926 | AA30: =IF(AND(ISNUMBER(Y30),ISNUMBER(Z30),Y30>0,Z30>0),Y30/Z30,"") -> 2.2903982 | AB30: 44.309349 | AC30: 0.012634766 | AD30: 0.50410787 | AE30: FY ends late June. FY2026 interest_expense returned 0 (FY2025 178203000). TTM block (pe 53.5, EV 385.7B) differs from FY2026 year-end valuation (pe 71.0, EV 514.3B); copied as returned. FY2026 EBITDA/EV figures as returned.
A31: MA | B31: Mastercard Inc. | C31: Financials | D31: Consumer Finance | E31: USD | F31: STD | G31: 2025-12-31 | H31: 5 | I31: 32791 | J31: 0.13821985 | K31: 0.16416374 | L31: 0.57628618 | M31: 5 | N31: 16433 | O31: 0.50114361 | P31: 5 | Q31: 5 | R31: 0.94198826 | S31: 1.9323522 | T31: 8102 | U31: 0.39437305 | V31: 26.17313 | W31: -0.075180227 | X31: 0.018206215 | Y31: 33.017298 | Z31: 35.962057 | AA31: =IF(AND(ISNUMBER(Y31),ISNUMBER(Z31),Y31>0,Z31>0),Y31/Z31,"") -> 0.91811483 | AB31: 24.328065 | AC31: 0.030932939 | AD31: 0.1364896 | AE31: Very small equity (buybacks) so ROE/price_to_book extreme as returned; cost_of_revenue 0 so gross_profit equals revenue as returned; TTM ROE 2.324587116608279 and debt_to_equity 4.39190875066833 as returned.
A32: META | B32: Meta Platforms Inc. | C32: Technology | D32: Internet Services | E32: USD | F32: STD | G32: 2025-12-31 | H32: 5 | I32: 200966 | J32: 0.19893831 | K32: 0.22167038 | L32: 0.41437855 | M32: 5 | N32: 46109 | O32: 0.22943682 | P32: 5 | Q32: 5 | R32: 0.29965219 | S32: 0.27829665 | T32: 2305 | U32: 0.022047289 | V32: 71.481545 | W32: -0.047372317 | X32: 0.10164406 | Y32: 28.563731 | Z32: 23.791548 | AA32: =IF(AND(ISNUMBER(Y32),ISNUMBER(Z32),Y32>0,Z32>0),Y32/Z32,"") -> 1.2005831 | AB32: 18.097181 | AC32: 0.020950257 | AD32: 0.26450596 | AE32: FY2025 income_tax 25474000000 (high vs prior year). Dividends began FY2024.
A33: MRK | B33: Merck & Co. Inc. | C33: Health Care | D33: Pharmaceuticals | E33: USD | F33: STD | G33: 2025-12-31 | H33: 5 | I33: 64926 | J33: 0.030772503 | K33: 0.011812742 | L33: 0.3617349 | M33: 5 | N33: 12360 | O33: 0.19037058 | P33: 5 | Q33: 5 | R33: 0.20933917 | S33: 0.34662565 | T33: 35969 | U33: 1.2726983 | V33: 17.307296 | W33: -0.013768686 | X33: 0 | Y33: 113.94048 | Z33: 14.852713 | AA33: =IF(AND(ISNUMBER(Y33),ISNUMBER(Z33),Y33>0,Z33>0),Y33/Z33,"") -> 7.6713577 | AB33: 28.919703 | AC33: 0.045161536 | AD33: 0.032915932 | AE33: FY2023 net income 365000000 and eps 0.14 (distorted by acquired IPR&D charge) so fy_pe_ratio 778.7 as returned. TTM net_margin 0.0478 and pe 113.9 are TTM figures as returned and differ sharply from FY2025 (TTM likely includes a large one-time charge). FY2026 EPS estimate 2.66326 as returned. FY2025 SBC returned as 0. Tearsheet source FMP.
A34: MRSH | B34: Marsh & McLennan Cos. Inc. | C34: Financials | D34: Insurance Brokers | E34: USD | F34: STD | G34: 2025-12-31 | H34: 5 | I34: 26981 | J34: 0.092000315 | K34: 0.10315643 | L34: 0.23064379 | M34: 5 | N34: 5001 | O34: 0.18535266 | P34: 5 | Q34: 5 | R34: 0.14426651 | S34: 0.27162912 | T34: 18762 | U34: 2.5371197 | V34: 6.4822917 | W34: -0.02970297 | X34: 0.014602869 | Y34: 21.519488 | Z34: 25.746667 | AA34: =IF(AND(ISNUMBER(Y34),ISNUMBER(Z34),Y34>0,Z34>0),Y34/Z34,"") -> 0.83581648 | AB34: 17.583872 | AC34: 0.056540463 | AD34: 0.058911118 | AE34: Ticker MRSH resolved to Marsh & McLennan Cos. Inc. (listing XNYS:MRSH, id 9B5968). Tangible book value negative (tangible_book_value_per_share FY2025 -29.23). EPS estimate (2026 10.45) is above FY2025 diluted EPS 8.43 as returned. total_equity includes minority interest (FY2025 total_stockholders_equity 15100000000).
A35: MS | B35: Morgan Stanley Co. | C35: Financials | D35: Investment Services | E35: USD | F35: FIN | G35: 2025-12-31 | H35: 5 | I35: 114983 | J35: 0.22546856 | K35: 0.11477047 | L35: 0.19093257 | M35: 5 | N35: 46100 | O35: 0.40092883 | P35: 2 | Q35: 3 | R35: 0.35952115 | S35: 0.14967333 | T35: -64411 | U35: -2.4203743 | V35: 0.44788543 | W35: -0.070052539 | X35: 0.016750302 | Y35: 15.146302 | Z35: 15.636816 | AA35: =IF(AND(ISNUMBER(Y35),ISNUMBER(Z35),Y35>0,Z35>0),Y35/Z35,"") -> 0.96863085 | AB35: 21.658093 | AC35: -0.052774125 | AD35: -0.28913086 | AE35: Bank/broker format: OCF/FCF swing wildly (negative FY2022-2024) and are not meaningful; debt/net debt ratios not meaningful. FY2025 revenue 114983000000 vs FY2026 SALES estimate 81737866786 (basis mismatch as returned). Entity name returned as 'Morgan Stanley Co.'. Tearsheet source FMP.
A36: MSFT | B36: Microsoft Corp. | C36: Technology | D36: Software | E36: USD | F36: STD | G36: 2026-06-30 | H36: 5 | I36: 331839 | J36: 0.16123979 | K36: 0.17788687 | L36: 0.46780818 | M36: 5 | N36: 66987 | O36: 0.20186597 | P36: 5 | Q36: 5 | R36: 0.24807658 | S36: 0.30233483 | T36: 51965.3 | U36: 0.25041225 | V36: 50.880695 | W36: -0.0025428266 | X36: 0.037382586 | Y36: 30.063889 | Z36: 35.034979 | AA36: =IF(AND(ISNUMBER(Y36),ISNUMBER(Z36),Y36>0,Z36>0),Y36/Z36,"") -> 0.85811065 | AB36: 19.423581 | AC36: 0.016670332 | AD36: 0.17763583 | AE36: Fiscal year ends June 30; provider labels FY ended 2026-06-30 as fiscal_year 2026; estimates fiscal_year 2027 and 2028 are the first two future FYs. Provider capex FY2026 (-115948000000) includes the returned value as-is. fy_market_cap and fy multiples for FY2026 as returned. Provider FMP.
A37: MU | B37: Micron Technology Inc. | C37: Technology | D37: Semiconductors | E37: USD | F37: STD | G37: 2026-09-03 | H37: 5 | I37: 133188 | J37: 1.0464668 | K37: 2.5632725 | L37: 0.75012013 | M37: 4 | N37: 58963 | O37: 0.44270505 | P37: 4 | Q37: 5 | R37: 0.7882957 | S37: 0.61403547 | T37: -38255 | U37: -0.34964811 | V37: 942.51887 | W37: 0.045745654 | X37: 0.010008409 | Y37: 12.553047 | Z37: 14.329388 | AA37: =IF(AND(ISNUMBER(Y37),ISNUMBER(Z37),Y37>0,Z37>0),Y37/Z37,"") -> 0.87603513 | AB37: 9.4825703 | AC37: 0.049415647 | AD37: 1.0808049 | AE37: FY ends ~Sept 3 2026 (53-week). FY2026 figures extremely large vs FY2025 (revenue 133.2B vs 37.4B, EPS 74.33 vs 7.59); copied exactly as returned, not verified against filings.
A38: NFLX | B38: Netflix Inc. | C38: Consumer Services | D38: Entertainment Production | E38: USD | F38: STD | G38: 2025-12-31 | H38: 5 | I38: 45183.036 | J38: 0.12639718 | K38: 0.15851069 | L38: 0.29494705 | M38: 5 | N38: 9461.053 | O38: 0.20939392 | P38: 4 | Q38: 5 | R38: 0.32883645 | S38: 0.41258687 | T38: 5400.477 | U38: 0.17850092 | V38: 17.162178 | W38: -0.043376986 | X38: 0.008154587 | Y38: 22.094427 | Z38: 39.585366 | AA38: =IF(AND(ISNUMBER(Y38),ISNUMBER(Z38),Y38>0,Z38>0),Y38/Z38,"") -> 0.55814634 | AB38: 8.6369421 | AC38: 0.036999004 | AD38: 0.13350504 | AE38: Share counts appear split-adjusted (~10-for-1) in the returned data; TTM key metrics (pe 22.09, ev_to_ebitda 8.64) differ markedly from FY2025 values (36.3, 13.3) - copied as returned.
A39: NOW | B39: ServiceNow Inc. | C39: Technology | D39: Application Software | E39: USD | F39: STD | G39: 2025-12-31 | H39: 5 | I39: 13278 | J39: 0.22376518 | K39: 0.20884924 | L39: 0.13737009 | M39: 5 | N39: 4576 | O39: 0.34463022 | P39: 5 | Q39: 5 | R39: 0.15864362 | S39: 0.13483493 | T39: -3881 | U39: -1.294098 | V39: 79.304348 | W39: 0.028815683 | X39: 0.14723603 | Y39: 88.571429 | Z39: 153.63768 | AA39: =IF(AND(ISNUMBER(Y39),ISNUMBER(Z39),Y39>0,Z39>0),Y39/Z39,"") -> 0.57649548 | AB39: 43.285043 | AC39: 0.031570636 | AD39: 0.2208272 | AE39: Estimate EPS (4.07 for FY2026) not comparable to reported FY2025 EPS 1.67 / shares 1.047B; possible split/basis mismatch in source (not verified). TTM ratios block returned TTM interest_coverage/debt_to_equity differing from FY2025.
... A41: PGR | B41: Progressive Corp. | C41: Financials | D41: Property and Casualty Insurance | E41: USD | F41: FIN | G41: 2025-12-31 | H41: 5 | I41: 87637 | J41: 0.20903783 | K41: 0.16317375 | L41: 0.16229446 | M41: 5 | N41: 17200 | O41: 0.19626414 | P41: 5 | Q41: 5 | R41: 0.64635124 | S41: 0.37291825 | T41: -12939 | U41: -0.87343054 | V41: 51.161871 | W41: 0.0018736161 | X41: 0.0015062131 | Y41: 11.025025 | Z41: 18.040422 | AA41: =IF(AND(ISNUMBER(Y41),ISNUMBER(Z41),Y41>0,Z41>0),Y41/Z41,"") -> 0.61112901 | AB41: 8.9357397 | AC41: 0.12345543 | AD41: 0.0092287457 | AE41: Insurer format: cost_of_revenue 61807000000 FY2025; total_debt is long-term debt only. TTM debt_to_equity 1.709 vs FY2025 0.227; TTM price_to_book 26.16 vs FY2025 4.40; TTM current_ratio 1.600 vs FY2025 0.586 (not comparable). FY2025 cash_and_short_term_investments 19836000000 vs 76090000000 FY2024 as returned. EPS estimate 2026 (18.287) is below FY2025 diluted EPS (19.23); 2027 estimate 16.25884.
A42: PM | B42: Philip Morris International Inc. | C42: Consumer Goods | D42: Tobacco | E42: USD | F42: STD | G42: 2025-12-31 | H42: 5 | I42: 40648 | J42: 0.085701522 | K42: 0.073129521 | L42: 0.36636489 | M42: 5 | N42: 10664 | O42: 0.26234993 | P42: 5 | Q42: 5 | R42: 0.32738778 | T42: 43963 | U42: 2.3482 | V42: 9.3837429 | W42: 0.0038659794 | X42: 0 | Y42: 28.844109 | Z42: 18.741036 | AA42: =IF(AND(ISNUMBER(Y42),ISNUMBER(Z42),Y42>0,Z42>0),Y42/Z42,"") -> 1.5390883 | AB42: 19.02184 | AC42: 0.04065852 | AD42: 0.07178771 | AE42: Negative total equity. FY2025 SBC and FY2024/2023 SBC returned as 0. Tearsheet source FMP. fy_market_cap from key_metrics.
A43: SCHW | B43: The Charles Schwab Corp. | C43: Financials | D43: Investment Services | E43: USD | F43: FIN | G43: 2025-12-31 | H43: 5 | I43: 27675 | J43: 0.074522435 | K43: 0.064464018 | L43: 0.41405601 | M43: 5 | N43: 8763 | O43: 0.31663957 | P43: 5 | Q43: 5 | R43: 0.019516721 | S43: 0.17909965 | T43: -77155 | U43: -6.0178613 | V43: 3.0524774 | W43: -0.061774023 | X43: 0.011454381 | Y43: 17.418478 | Z43: 24.67 | AA43: =IF(AND(ISNUMBER(Y43),ISNUMBER(Z43),Y43>0,Z43>0),Y43/Z43,"") -> 0.70605911 | AB43: 10.603229 | AC43: 0.022156664 | AD43: 0.020399855 | AE43: Bank/broker format: gross_profit/revenue/interest_expense definitions differ (cost_of_revenue = interest expense); FCF, capex, debt, cash metrics are not meaningful in the usual sense. total_equity 49425000000 includes preferred (preferred_stock 6763000000). TTM current_ratio and cash conversion metrics distorted.
A44: SHOP | B44: Shopify Inc. | C44: Industrials | D44: Business Support Services | E44: USD | F44: STD | G44: 2025-12-31 | H44: 5 | I44: 11758.294 | J44: 0.28051724 | K44: 0.32413221 | L44: 0.16363794 | M44: 4 | N44: 2042.1336 | O44: 0.17367601 | P44: 4 | Q44: 4 | R44: 0.19255655 | S44: 0.092967342 | T44: -5579 | U44: -2.8535581 | V44: 999 | W44: 0.030550279 | X44: 0.038185812 | Y44: 120 | Z44: 117.67642 | AA44: =IF(AND(ISNUMBER(Y44),ISNUMBER(Z44),Y44>0,Z44>0),Y44/Z44,"") -> 1.0197455 | AB44: 96.259982 | AC44: 0.010137028 | AD44: 0.27952088 | AE44: Foreign (Canadian) issuer but reports in USD. FY2021 and FY2024 net income inflated by investment gains; FY2022 large loss (equity investment writedowns); FY2023 pe_ratio 777 and ev_to_ebitda -12425 reflect near-zero earnings/EBITDA. FY2025 filing_date equals report_date (2025-12-31) and some FY2025 cash flow values have non-rounded figures (looks derived). interest_expense 0 in most years. FY2025 EPS 0.96.
A45: SPGI | B45: S&P Global Inc. | C45: Consumer Services | D45: Publishing | E45: USD | F45: STD | G45: 2025-12-31 | H45: 5 | I45: 15336 | J45: 0.11107613 | K45: 0.079391892 | L45: 0.4224048 | M45: 5 | N45: 5456 | O45: 0.35576421 | P45: 5 | Q45: 5 | R45: 0.1054071 | S45: 0.12367227 | T45: 12399 | U45: 1.6117249 | V45: 22.571429 | W45: -0.042072214 | X45: 0.015388628 | Y45: 25.087645 | Z45: 37.574045 | AA45: =IF(AND(ISNUMBER(Y45),ISNUMBER(Z45),Y45>0,Z45>0),Y45/Z45,"") -> 0.66768549 | AB45: 16.180942 | AC45: 0.045863175 | AD45: -0.032267748 | AE45: total_equity includes minority interest (36152000000; stockholders equity 31235000000 in FY2025). Tearsheet source FMP.
A46: SYK | B46: Stryker Corp. | C46: Health Care | D46: Medical Equipment | E46: USD | F46: STD | G46: 2025-12-31 | H46: 5 | I46: 25116 | J46: 0.1083048 | K46: 0.11157336 | L46: 0.19465679 | M46: 5 | N46: 4283 | O46: 0.17052875 | P46: 5 | Q46: 5 | R46: 0.11136995 | S46: 0.14478145 | T46: 12260 | U46: 1.9417168 | V46: 8.0543657 | W46: 0 | X46: 0.0096751075 | Y46: 29.044193 | Z46: 41.398115 | AA46: =IF(AND(ISNUMBER(Y46),ISNUMBER(Z46),Y46>0,Z46>0),Y46/Z46,"") -> 0.7015825 | AB46: 17.915235 | AC46: 0.043401307 | AD46: 0.082487554 | AE46: FY ends Dec. Tangible book value negative. FY2025 EPS 8.4 is GAAP diluted vs FY2026 consensus 14.96 (likely adjusted basis).
A47: TJX | B47: TJX Companies Inc. | C47: Consumer Services | D47: Apparel Retailers | E47: USD | F47: STD | G47: 2026-01-31 | H47: 5 | I47: 60372 | J47: 0.065304931 | K47: 0.071185238 | L47: 0.11889618 | M47: 5 | N47: 4917 | O47: 0.081445041 | P47: 5 | Q47: 5 | R47: 0.32498252 | S47: 0.53915604 | T47: 7259 | U47: 0.84940323 | V47: 97 | W47: -0.044991511 | X47: 0.0035446896 | Y47: 26.232902 | Z47: 27.286667 | AA47: =IF(AND(ISNUMBER(Y47),ISNUMBER(Z47),Y47>0,Z47>0),Y47/Z47,"") -> 0.9613817 | AB47: 18.157426 | AC47: 0.037572012 | AD47: 0.060407724 | AE47: Fiscal year ends January (fiscal_year 2026 = FYE 2026-01-31). Estimates are for FY2027 and FY2028. FY2022 cash flow values returned with non-round decimals (capex -1044794000, dividends -1251833000). TTM and FY2026 differ (TTM ROE 0.598 vs FY 0.539). Reported goodwill_and_intangible_assets tiny (96000000) vs total assets; operating-lease obligations included in total_debt.
A48: TSM | B48: TSMC Ltd. (Taiwan) | C48: Technology | D48: Semiconductors | E48: TWD | F48: STD | G48: 2025-12-31 | H48: 5 | I48: 3809054 | J48: 0.18937969 | K48: 0.31604999 | L48: 0.50816948 | M48: 5 | N48: 1086331 | O48: 0.28519706 | P48: 5 | Q48: 5 | R48: 0.44236483 | S48: 0.31458478 | T48: -2004011.3 | U48: -0.73561621 | V48: 156.47392 | W48: 5.2720505e-05 | X48: 0 | Y48: 28.862872 | Z48: 23.399758 | AA48: =IF(AND(ISNUMBER(Y48),ISNUMBER(Z48),Y48>0,Z48>0),Y48/Z48,"") -> 1.2334688 | AB48: 19.149917 | AC48: 0.017321347 | AD48: 0.43715969 | AE48: FOREIGN: all figures in TWD (New Taiwan dollars), not USD; EPS is per ordinary share (TWD), not per ADR. Stock-based compensation returned 0 for FY2025. report dates equal to FY end (filing_date placeholders).
A49: V | B49: Visa Inc. | C49: Financials | D49: Consumer Finance | E49: USD | F49: STD | G49: 2025-09-30 | H49: 5 | I49: 40000 | J49: 0.10921242 | K49: 0.11339977 | L49: 0.59985 | M49: 5 | N49: 21577 | O49: 0.539425 | P49: 5 | Q49: 5 | R49: 0.4612771 | S49: 0.52910918 | T49: 3184 | U49: 0.12244741 | V49: 40.736842 | W49: -0.079588015 | X49: 0.022425 | Y49: 33.381054 | Z49: 28.228953 | AA49: =IF(AND(ISNUMBER(Y49),ISNUMBER(Z49),Y49>0,Z49>0),Y49/Z49,"") -> 1.1825112 | AB49: 25.604939 | AC49: 0.02864549 | AD49: 0.2705486 | AE49: Fiscal year ends Sept 30. Latest reported FY2025 (2025-09-30); FY2026 (ends 2026-09-30) not yet reported in income statement and no FY2026 estimate was returned; estimates returned start at FY2027 so those are listed. FY2025 revenue exactly 40000000000 as returned. TTM key metrics differ from FY2025.
A50: VRTX | B50: Vertex Pharmaceuticals Inc. | C50: Health Care | D50: Biotechnology | E50: USD | F50: STD | G50: 2025-12-31 | H50: 5 | I50: 12074.6 | J50: 0.10576393 | K50: 0.095688787 | L50: 0.39427393 | M50: 4 | N50: 3193.8 | O50: 0.26450566 | P50: 4 | Q50: 4 | R50: 0.23598581 | S50: 0.2117884 | T50: -2728.6 | U50: -0.56071348 | V50: 357.94737 | W50: -0.0042454651 | X50: 0.056805194 | Y50: 28.652125 | Z50: 26.559279 | AA50: =IF(AND(ISNUMBER(Y50),ISNUMBER(Z50),Y50>0,Z50>0),Y50/Z50,"") -> 1.078799 | AB50: 22.132584 | AC50: 0.030133806 | AD50: 0.097069141 | AE50: FY2024 negative net income/EPS/OCF/FCF (acquired IPR&D charge), fy_pe_ratio -193.6 and fy_ev_to_ebitda 207.4 as returned. Tearsheet source FMP.
A51: WFC | B51: Wells Fargo & Co. | C51: Financials | D51: Banks | E51: USD | F51: FIN | G51: 2025-12-31 | H51: 5 | I51: 123529 | J51: 0.139711 | K51: -0.014896688 | L51: 0.20399258 | M51: 5 | N51: -19001 | O51: -0.15381813 | P51: 3 | Q51: 3 | R51: 0.14508888 | S51: 0.11657689 | T51: -45831 | U51: -1.3925316 | V51: 0.63266382 | W51: -0.16148032 | X51: 0 | Y51: 11.537396 | Z51: 12.935543 | AA51: =IF(AND(ISNUMBER(Y51),ISNUMBER(Z51),Y51>0,Z51>0),Y51/Z51,"") -> 0.89191431 | AB51: 9.20186 | AC51: 0.076101869 | AD51: -0.28117287 | AE51: BANK FORMAT: provider generic fundamentals are not meaningful for a bank (operating_cash_flow negative/volatile, capex 0, stock_based_compensation 0, total_assets 2.1T, huge deposit-driven current liabilities, current_ratio/net_debt_to_ebitda/interest_coverage not comparable, interest_expense in revenue-cost structure). FY2021 gross_profit (83321000000) exceeds revenue (83081000000) as returned. Revenue FY2025 vs estimate FY2026 differ in basis (123.5B vs 88.8B est.) as returned. Provider FMP.
A52: AAPL | B52: Apple Inc. | C52: Technology | D52: Computer Hardware | E52: USD | F52: STD | G52: 2025-09-27 | H52: 5 | I52: 416161 | J52: 0.018125357 | K52: 0.064255118 | L52: 0.319708 | M52: 5 | N52: 98767 | O52: 0.23732882 | P52: 5 | Q52: 5 | R52: 0.79984096 | S52: 1.5191298 | T52: 57680 | U52: 0.39937131 | V52: 999 | W52: -0.08092225 | X52: 0.030908711 | Y52: 39.232877 | Z52: 27.793831 | AA52: =IF(AND(ISNUMBER(Y52),ISNUMBER(Z52),Y52>0,Z52>0),Y52/Z52,"") -> 1.4115678 | AB52: 29.988906 | AC52: 0.027293216 | AD52: 0.26139038 | AE52: Fiscal year ends late September. goodwill_and_intangible_assets is 0 in provider data (Apple reports none). interest_expense is 0 for FY2025 and FY2024 and interest_coverage TTM is 0 as returned. No fiscal_year 2026 estimate returned; first two returned are 2027 and 2028. Provider FMP.
A53: ABT | B53: Abbott Laboratories Inc. | C53: Health Care | D53: Medical Equipment | E53: USD | F53: STD | G53: 2025-12-31 | H53: 5 | I53: 44328 | J53: 0.0051279442 | K53: 0.056686532 | L53: 0.18155568 | M53: 5 | N53: 7395 | O53: 0.16682458 | P53: 5 | Q53: 5 | R53: 0.10794615 | S53: 0.12362851 | T53: 6128 | U53: 0.51396461 | V53: 23.601173 | W53: -0.0096371882 | X53: 0.014979246 | Y53: 32.752412 | Z53: 33.354545 | AA53: =IF(AND(ISNUMBER(Y53),ISNUMBER(Z53),Y53>0,Z53>0),Y53/Z53,"") -> 0.98194747 | AB53: 17.838523 | AC53: 0.049961293 | AD53: 0.13485876 | AE53: FY2024 net_income (13402000000) includes a large negative income_tax (-6389000000) as returned. Estimate EPS (5.51 for FY2026) is on a different basis than reported GAAP eps_diluted (3.72 FY2025) as returned. Sales estimate FY2026 (50.3B) vs FY2025 revenue 44.3B as returned. Provider FMP.
A54: AMD | B54: Advanced Micro Devices Inc. | E54: USD | F54: STD | G54: 2025-12-27 | H54: 5 | I54: 34639 | J54: 0.13643599 | K54: 0.34337793 | L54: 0.1066428 | M54: 5 | N54: 6735 | O54: 0.19443402 | P54: 5 | Q54: 5 | R54: 0.075772863 | S54: 0.068810616 | T54: -6080 | U54: -0.83573883 | V54: 28.198473 | W54: 0.04137492 | X54: 0.047287739 | Y54: 149.0533 | Z54: 80.520599 | AA54: =IF(AND(ISNUMBER(Y54),ISNUMBER(Z54),Y54>0,Z54>0),Y54/Z54,"") -> 1.8511202 | AB54: 89.269686 | AC54: 0.0087750398 | AD54: 0.47388483 | AE54: sector/industry not returned in requested sections (null). Fiscal year ends late December (52/53-week). FY2025 income_tax -103000000 (tax benefit), net_income 4335000000 vs continuing ops 4269000000. FY2021-FY2022 balance sheet pre-Xilinx scale vs later years (goodwill_and_intangible_assets 612000000 to 48295000000). TTM pe_ratio 149.1 and ev_to_ebitda 89.3 differ from FY2025 (80.5, 47.8): price-date basis. No dividends paid.
A55: AMGN | B55: Amgen Inc. | C55: Health Care | D55: Biotechnology | E55: USD | F55: STD | G55: 2025-12-31 | H55: 5 | I55: 36741 | J55: 0.11756261 | K55: 0.099240067 | L55: 0.29057456 | M55: 5 | N55: 8100 | O55: 0.22046215 | P55: 5 | Q55: 5 | R55: 0.15580219 | S55: 0.89062139 | T55: 45475 | U55: 2.6911469 | V55: 3.8751361 | W55: 0.0018484288 | X55: 0.01344547 | Y55: 25.674377 | Z55: 22.840893 | AA55: =IF(AND(ISNUMBER(Y55),ISNUMBER(Z55),Y55>0,Z55>0),Y55/Z55,"") -> 1.1240531 | AB55: 15.248431 | AC55: 0.045143401 | AD55: 0.061299286 | AE55: Low positive equity (8658000000 FY2025). Tearsheet source FMP.
A56: ARM | B56: ARM Holdings PLC | C56: Technology | D56: Semiconductors | E56: USD | F56: STD | G56: 2026-03-31 | H56: 5 | I56: 4920 | J56: 0.22460905 | K56: 0.22785126 | L56: 0.18455285 | M56: 5 | N56: 979 | O56: 0.19898374 | P56: 5 | Q56: 5 | R56: 0.13950214 | S56: 0.10909969 | T56: -3144 | U56: -2.2361309 | V56: 999 | W56: 0.040880021 | X56: 0.21382114 | Y56: 258.99948 | Z56: 142.38667 | AA56: =IF(AND(ISNUMBER(Y56),ISNUMBER(Z56),Y56>0,Z56>0),Y56/Z56,"") -> 1.8189869 | AB56: 193.54679 | AC56: 0.0054935892 | AD56: 0.23484499 | AE56: FY ends March. FY2022 balance sheet not returned (null); FY2022 ev_to_ebitda 0 as returned. interest_expense 0 as returned. capex negative as returned.
A57: AVGO | B57: Broadcom Inc. | C57: Technology | D57: Semiconductors | E57: USD | F57: STD | G57: 2025-11-02 | H57: 5 | I57: 63887 | J57: 0.24378426 | K57: 0.23874433 | L57: 0.39889179 | M57: 5 | N57: 26914 | O57: 0.42127506 | P57: 5 | Q57: 5 | R57: 0.24029088 | S57: 0.28448064 | T57: 48958 | U57: 1.4103244 | V57: 7.9389408 | W57: 0.14728132 | X57: 0.11845915 | Y57: 44.011166 | Z57: 33.636943 | AA57: =IF(AND(ISNUMBER(Y57),ISNUMBER(Z57),Y57>0,Z57>0),Y57/Z57,"") -> 1.3084176 | AB57: 32.888365 | AC57: 0.023367525 | AD57: 0.65899778 | AE57: Fiscal year ends early November (FY2026 ends 2026-11-02, not yet reported). FY2025 income_tax negative (-397000000). FY2024 net_income 5895000000 (continuing ops 6168000000). FY2026+ are estimates.
A58: BMY | B58: Bristol-Myers Squibb Co. | C58: Health Care | D58: Pharmaceuticals | E58: USD | F58: STD | G58: 2025-12-31 | H58: 5 | I58: 48195 | J58: 0.014491777 | K58: -0.002173913 | L58: 0.28475983 | M58: 4 | N58: 12845 | O58: 0.26652142 | P58: 5 | Q58: 5 | R58: 0.19722695 | S58: 0.38117367 | T58: 36466 | U58: 2.3943533 | V58: 7.2575357 | W58: -0.048928239 | X58: 0.011474219 | Y58: 12.503304 | Z58: 17.691623 | AA58: =IF(AND(ISNUMBER(Y58),ISNUMBER(Z58),Y58>0,Z58>0),Y58/Z58,"") -> 0.70673583 | AB58: 8.8827267 | AC58: 0.099500816 | AD58: 0.032774133 | AE58: FY2024 net loss (acquired IPR&D charges). FY2025 EPS 3.45 GAAP vs FY2026 consensus 6.96 (likely non-GAAP basis) as returned. total_equity includes minority interest. Tangible book value negative.
A59: BX | B59: Blackstone Inc. | C59: Financials | D59: Diversified Capital Markets | E59: USD | F59: FIN | G59: 2025-12-31 | H59: 5 | I59: 13828.896 | J59: 0.22898484 | K59: 0.21580964 | L59: 0.51907875 | M59: 5 | N59: 1744.898 | O59: 0.12617768 | P59: 5 | Q59: 5 | R59: 1.3669938 | S59: 0.13798228 | T59: 10674.924 | U59: 1.4796877 | V59: 14.121755 | W59: 0.053960471 | X59: 0.14091356 | Y59: 25.54 | Z59: 39.726804 | AA59: =IF(AND(ISNUMBER(Y59),ISNUMBER(Z59),Y59>0,Z59>0),Y59/Z59,"") -> 0.64289088 | AB59: 17.916902 | AC59: 0.031802624 | AD59: 0.044613862 | AE59: Asset manager / non-standard format: net_income (bottom_line_net_income) is attributable to common; net_income_from_continuing_operations FY2025=6046623000 (includes minority interest). total_equity includes minority_interest 13215646000 (stockholders equity 8665526000). cost/R&D fields odd (cost_of_revenue equals interest expense in some years). SBC 0 in FY2021-2024 (not reported by source). FY2026+ are estimates.
A60: C | B60: Citigroup Inc. | C60: Financials | D60: Banks | E60: USD | F60: FIN | G60: 2025-12-31 | H60: 5 | I60: 168285 | J60: 0.18858525 | K60: -0.014188053 | L60: 0.11782393 | M60: 5 | N60: -74152 | O60: -0.44063345 | P60: 2 | Q60: 2 | R60: 0.061625122 | S60: 0.066906118 | T60: 40362 | U60: 1.6677823 | V60: 0.23868451 | W60: -0.051774169 | X60: 0 | Y60: 13.990456 | Z60: 11.6733 | AA60: =IF(AND(ISNUMBER(Y60),ISNUMBER(Z60),Y60>0,Z60>0),Y60/Z60,"") -> 1.1985005 | AB60: 23.075461 | AC60: -0.10833683 | AD60: -0.42971644 | AE60: Bank format: FCF/OCF negative and not meaningful, total_debt/net debt ratios not meaningful, revenue FY2025 168285000000 vs estimates SALES FY2026 95970168528 (basis mismatch as returned). SBC returned as 0. Tearsheet source FMP.
A61: COP | B61: ConocoPhillips Co. | C61: Energy | D61: Integrated Oil and Gas | E61: USD | F61: STD | G61: 2025-12-31 | H61: 5 | I61: 58944 | J61: -0.091061747 | K61: 0.076701069 | L61: 0.19241992 | M61: 5 | N61: 7243 | O61: 0.12287934 | P61: 5 | Q61: 5 | R61: 0.11068783 | S61: 0.12386993 | T61: 16463 | U61: 0.64843042 | V61: 9.1987024 | W61: -0.019337909 | X61: 0 | Y61: 18.472884 | Z61: 12.681586 | AA61: =IF(AND(ISNUMBER(Y61),ISNUMBER(Z61),Y61>0,Z61>0),Y61/Z61,"") -> 1.4566699 | AB61: 6.7492864 | AC61: 0.059337943 | AD61: 0.23044534 | AE61: Provider classifies industry as Integrated Oil and Gas. stock_based_compensation is 0 for FY2023-FY2025 as returned (nonzero FY2021-22). goodwill_and_intangible_assets is 0 in all years as returned. FY2025 ebitda (25389000000) vs operating_income (11342000000) as returned. Provider FMP.
A62: COST | B62: Costco Wholesale Corp. | C62: Consumer Services | D62: Broadline Retailers | E62: USD | F62: STD | G62: 2026-08-30 | H62: 5 | I62: 303154 | J62: 0.077562835 | K62: 0.10143695 | L62: 0.038544766 | M62: 5 | N62: 9390 | O62: 0.030974356 | P62: 5 | Q62: 5 | R62: 0.39999783 | S62: 0.2576879 | T62: -12725 | U62: -0.88620377 | V62: 80.586207 | W62: -5.6249044e-05 | X62: 0.0030479558 | Y62: 46.166987 | Z62: 45.423003 | AA62: =IF(AND(ISNUMBER(Y62),ISNUMBER(Z62),Y62>0,Z62>0),Y62/Z62,"") -> 1.016379 | AB62: 28.822376 | AC62: 0.022068596 | AD62: 0.085291418 | AE62: Fiscal year ends late Aug/early Sep. FY2026 (report_date 2026-08-30, filed 2026-10-07) is already reported, so first two future estimate years are FY2027 and FY2028. FY2024 common_dividends_paid -9041000000 includes special dividend as returned. TTM equals FY2026 data (ratios TTM vs FY2026 differ slightly in ROE).
A63: DELL | B63: Dell Technologies Inc. | C63: Technology | D63: Computer Hardware | E63: USD | F63: STD | G63: 2026-01-30 | H63: 5 | I63: 113538 | J63: 0.035349839 | K63: 0.18804608 | L63: 0.074389191 | M63: 5 | N63: 8552 | O63: 0.075322799 | P63: 5 | Q63: 5 | R63: 0.38116767 | T63: 19975 | U63: 1.6853696 | V63: 5.4141026 | W63: -0.091804781 | X63: 0.0063679121 | Y63: 32.455689 | Z63: 12.772321 | AA63: =IF(AND(ISNUMBER(Y63),ISNUMBER(Z63),Y63>0,Z63>0),Y63/Z63,"") -> 2.5410955 | AB63: 22.045319 | AC63: 0.022366523 | AD63: 0.71381974 | AE63: FY ends late January/early February (fiscal_year label = year of Jan end, FY2026 ended 2026-01-30). Total equity negative in all five years, so debt_to_equity, return_on_equity and price_to_book are negative as returned. TTM valuation (pe 32.5, EV 405.6B) differs from FY2026 year-end (pe 12.8, EV 95.8B); copied as returned. FY2022 eps_diluted 7.02 vs net_income 5563000000 includes discontinued operations.
A64: DIS | B64: The Walt Disney Co. | C64: Consumer Services | D64: Entertainment Production | E64: USD | F64: STD | G64: 2025-09-27 | H64: 5 | I64: 94425 | J64: 0.045093923 | K64: 0.033537286 | L64: 0.14648663 | M64: 5 | N64: 10077 | O64: 0.10671962 | P64: 5 | Q64: 5 | R64: 0.070800052 | S64: 0.10822601 | T64: 39728 | U64: 2.0755446 | V64: 7.6335541 | W64: -0.008757526 | X64: 0.014434737 | Y64: 22.473251 | Z64: 54.526012 | AA64: =IF(AND(ISNUMBER(Y64),ISNUMBER(Z64),Y64>0,Z64>0),Y64/Z64,"") -> 0.41215652 | AB64: 9.9249816 | AC64: 0.04372524 | AD64: 0.12589971 | AE64: FY ends late Sept/early Oct. Estimates returned start at FY2027 (no FY2026 estimate row returned). net_income is net_income attributable (12404000000); net_income_from_continuing_operations was 13431000000. total_equity 114612000000 includes minority interest (total_stockholders_equity 109869000000).
A65: DUK | B65: Duke Energy Corp. | C65: Utilities | D65: Multiutilities | E65: USD | F65: UTIL/REIT | G65: 2025-12-31 | H65: 5 | I65: 32237 | J65: 0.038679714 | K65: 0.061929703 | L65: 0.26606074 | M65: 5 | N65: -1672 | O65: -0.051865868 | P65: 1 | Q65: 5 | R65: 0.047171321 | S65: 0.093702258 | T65: 90624 | U65: 5.7832802 | V65: 2.3602091 | W65: 0.0090909091 | X65: 0 | Y65: 17.623123 | Z65: 18.868651 | AA65: =IF(AND(ISNUMBER(Y65),ISNUMBER(Z65),Y65>0,Z65>0),Y65/Z65,"") -> 0.93398954 | AB65: 10.405566 | AC65: -0.046709779 | AD65: 0.042742883 | AE65: Utility; negative FCF (capex > OCF) all years; FY2025 gross_profit 10174000000 vs FY2024 15197000000 as returned (cost_of_revenue classification differs); TTM gross_margin 0.68 vs FY2025 0.3156 as returned. Cash 245000000.
A66: GILD | B66: Gilead Sciences Inc. | C66: Health Care | D66: Biotechnology | E66: USD | F66: STD | G66: 2025-12-31 | H66: 5 | I66: 29442 | J66: 0.02573618 | K66: 0.023927106 | L66: 0.39742545 | M66: 5 | N66: 9456 | O66: 0.32117383 | P66: 5 | Q66: 5 | R66: 0.24363591 | S66: 0.37624901 | T66: 15323 | U66: 1.1283505 | V66: 11.426758 | W66: -0.0055467512 | X66: 0.030364785 | Y66: -57.065385 | Z66: 17.944444 | AA66: =IF(AND(ISNUMBER(Y66),ISNUMBER(Z66),Y66>0,Z66>0),Y66/Z66,"") | AB66: 155.20176 | AC66: 0.071744556 | AD66: 0.043519946 | AE66: TTM figures are negative (TTM net_margin -0.106, pe -57.07, ev_to_ebitda 155.2) as returned, likely due to a large one-time charge in the latest quarters; FY2026 EPS estimate is negative (-0.42166) as returned. FY2024 net income 480000000 / eps 0.38 (IPR&D charge), fy_pe_ratio 243.08. Tearsheet source FMP.
A67: HD | B67: The Home Depot Inc. | C67: Consumer Services | D67: Home Improvement Retailers | E67: USD | F67: STD | G67: 2026-02-01 | H67: 5 | I67: 164683 | J67: 0.015185146 | K67: 0.032404679 | L67: 0.12684977 | M67: 5 | N67: 12646 | O67: 0.076789954 | P67: 5 | Q67: 5 | R67: 0.21495689 | S67: 1.1048154 | T67: 63961 | U67: 2.5446986 | V67: 8.6608624 | W67: -0.027317073 | X67: 0.0031697261 | Y67: 20.294693 | Z67: 23.539448 | AA67: =IF(AND(ISNUMBER(Y67),ISNUMBER(Z67),Y67>0,Z67>0),Y67/Z67,"") -> 0.86215668 | AB67: 13.749868 | AC67: 0.052111562 | AD67: 0.041810132 | AE67: Fiscal year ends ~Feb 1; provider labels FY ended 2026-02-01 as fiscal_year 2025. Estimates fiscal_year 2027 (report_date 2027-02-01) and 2028 are the first two future FYs as labeled by provider (no fiscal_year 2026 estimate returned). common_stock_repurchased is 0 in FY2025. Provider FMP.
A68: HOOD | B68: Robinhood Markets Inc. | C68: Financials | D68: Investment Services | E68: USD | F68: FIN | G68: 2025-12-31 | H68: 5 | I68: 4473 | J68: 0.48787476 | K68: 0.51575737 | L68: 0.46814219 | M68: 2 | N68: 1584 | O68: 0.35412475 | P68: 2 | Q68: 2 | R68: 0.16020337 | S68: 0.20576986 | T68: 1175 | U68: 0.53899083 | V68: 999 | W68: 0.045698213 | X68: 0.068186899 | Y68: 47.967532 | Z68: 38.318278 | AA68: =IF(AND(ISNUMBER(Y68),ISNUMBER(Z68),Y68>0,Z68>0),Y68/Z68,"") -> 1.2518186 | AB68: 49.541218 | AC68: 0.0017867393 | AD68: 0.18963248 | AE68: Broker format: balance sheet includes customer-related balances (short_term_debt 11.6B, receivables 18.4B); debt/leverage and working capital ratios not comparable to non-financials. FY2025 interest_expense returned 0 while FY2024 24000000. FY2021 eps_diluted -4.2671 and FY2023 -0.6073 as returned. TTM free_cash_flow_yield 0.0018 vs FY2025 0.0158 as returned.
A69: IBM | B69: IBM Corp. | C69: Technology | D69: Computer Services | E69: USD | F69: STD | G69: 2025-12-31 | H69: 5 | I69: 67536 | J69: 0.037181799 | K69: 0.076219464 | L69: 0.18496802 | M69: 5 | N69: 12102 | O69: 0.17919332 | P69: 5 | Q69: 5 | R69: 0.11552585 | S69: 0.32353929 | T69: 52683 | U69: 3.0480791 | V69: 6.455814 | W69: 0.039934493 | X69: 0.025393864 | Y69: 20.095197 | Z69: 26.074824 | AA69: =IF(AND(ISNUMBER(Y69),ISNUMBER(Z69),Y69>0,Z69>0),Y69/Z69,"") -> 0.77067429 | AB69: 15.479981 | AC69: 0.063731028 | AD69: 0.041975418 | AE69: total_equity includes minority_interest (FY2025 stockholders equity 32648000000). common_stock_repurchased returned 0 for FY2024 and FY2025. FY2022 net income depressed by pension/divestiture items. FY2026+ are estimates.
A70: ICE | B70: Intercontinental Exchange Inc. | C70: Financials | D70: Investment Services | E70: USD | F70: STD | G70: 2025-12-31 | H70: 5 | I70: 12638 | J70: 0.094612794 | K70: 0.074568489 | L70: 0.38740307 | M70: 5 | N70: 4289 | O70: 0.33937332 | P70: 5 | Q70: 5 | R70: 0.084720725 | S70: 0.1139664 | T70: 16663 | U70: 2.5083547 | V70: 6.268886 | W70: 0.018076542 | X70: 0.018832094 | Y70: 22.241913 | Z70: 30.578571 | AA70: =IF(AND(ISNUMBER(Y70),ISNUMBER(Z70),Y70>0,Z70>0),Y70/Z70,"") -> 0.72736926 | AB70: 16.162312 | AC70: 0.054607505 | AD70: -0.12172407 | AE70: Exchange/clearing operator: balance sheet includes large clearing-house items (other_current_assets ~79B, total_assets ~137B). TTM inventory_turnover/days_of_inventory/cash_conversion_cycle values are anomalous as returned (cash_conversion_cycle 16162). Estimate EPS basis (8.17 for FY2026) is higher than reported GAAP eps_diluted (5.77) as returned. Provider FMP.
A71: LIN | B71: Linde PLC | C71: Basic Materials | D71: Commodity Chemicals | E71: USD | F71: STD | G71: 2025-12-31 | H71: 5 | I71: 33986 | J71: 0.0061760606 | K71: 0.029722769 | L71: 0.27228859 | M71: 5 | N71: 5089 | O71: 0.14973813 | P71: 5 | Q71: 5 | R71: 0.11853715 | S71: 0.17357389 | T71: 21933 | U71: 1.6849504 | V71: 19.943966 | W71: -0.070105825 | X71: 0.0039133761 | Y71: 31.470437 | Z71: 32.33937 | AA71: =IF(AND(ISNUMBER(Y71),ISNUMBER(Z71),Y71>0,Z71>0),Y71/Z71,"") -> 0.9731308 | AB71: 18.607065 | AC71: 0.021934166 | AD71: 0.068874356 | AE71: Irish-domiciled (country Ireland); resolved via 'Linde plc' without countries filter (query 'LIN' with US filter returned no match). Listing XNAS:LIN/XNYS:LIN.
A72: MCD | B72: McDonald's Corp. | C72: Consumer Services | D72: Restaurants and Bars | E72: USD | F72: STD | G72: 2025-12-31 | H72: 5 | I72: 26885 | J72: 0.050637859 | K72: 0.037229938 | L72: 0.46096336 | M72: 5 | N72: 7186 | O72: 0.26728659 | P72: 5 | Q72: 5 | R72: 0.187381 | T72: 54040 | U72: 3.6817005 | V72: 7.8337547 | W72: -0.03358964 | X72: 0.0061372513 | Y72: 19.139384 | Z72: 25.495271 | AA72: =IF(AND(ISNUMBER(Y72),ISNUMBER(Z72),Y72>0,Z72>0),Y72/Z72,"") -> 0.75070331 | AB72: 14.697354 | AC72: 0.046249476 | AD72: 0.047513068 | AE72: Negative total equity in all years (ROE, debt_to_equity, price_to_book negative/meaningless). FY2022 and FY2021 values copied as returned (some with decimals in raw dollars).
A73: MDT | B73: Medtronic PLC | C73: Health Care | D73: Medical Equipment | E73: USD | F73: STD | G73: 2026-04-24 | H73: 5 | I73: 36364 | J73: 0.052076036 | K73: 0.084294958 | L73: 0.17784072 | M73: 5 | N73: 5426 | O73: 0.14921351 | P73: 5 | Q73: 5 | R73: 0.074243675 | S73: 0.095861959 | T73: 18741 | U73: 1.9105923 | V73: 9.0447552 | W73: -0.033538415 | X73: 0.012567374 | Y73: 22.396088 | Z73: 27.829333 | AA73: =IF(AND(ISNUMBER(Y73),ISNUMBER(Z73),Y73>0,Z73>0),Y73/Z73,"") -> 0.80476552 | AB73: 14.121507 | AC73: 0.052297357 | AD73: 0.073750011 | AE73: find_securities with countries=[US] did not return Medtronic; resolved via query 'Medtronic plc' without country filter (Ireland-incorporated, XNYS:MDT). Fiscal year ends late April. Estimates are on an EPS basis that looks non-GAAP/adjusted versus reported GAAP eps_diluted (3.73 vs 5.98 estimate) - copied as returned. TTM ratios contain odd values (negative inventory_turnover, days_of_inventory_outstanding). Provider FMP.
A74: PEP | B74: PepsiCo Inc. | C74: Consumer Goods | D74: Soft Drinks | E74: USD | F74: STD | G74: 2025-12-27 | H74: 5 | I74: 93925 | J74: 0.028259093 | K74: 0.02254665 | L74: 0.14363588 | M74: 5 | N74: 7672 | O74: 0.081682193 | P74: 5 | Q74: 5 | R74: 0.17495469 | S74: 0.40103178 | T74: 40371 | U74: 2.597375 | V74: 12.03479 | W74: -0.010093727 | X74: 0.0030662763 | Y74: 15.894605 | Z74: 25.772382 | AA74: =IF(AND(ISNUMBER(Y74),ISNUMBER(Z74),Y74>0,Z74>0),Y74/Z74,"") -> 0.61673013 | AB74: 11.260952 | AC74: 0.060510314 | AD74: 0.05696718 | AE74: FY2025 report_date 2025-12-27 (52/53 week year). Analyst EPS 2026 8.42 is core/adjusted basis vs GAAP 6.00 in FY2025, as returned (not adjusted).
A75: PG | B75: Procter & Gamble Co. | C75: Consumer Goods | D75: Nondurable Household Products | E75: USD | F75: STD | G75: 2026-06-30 | H75: 5 | I75: 87032 | J75: 0.020025694 | K75: 0.032604053 | L75: 0.22690505 | M75: 5 | N75: 15147 | O75: 0.17403943 | P75: 5 | Q75: 5 | R75: 0.19592992 | S75: 0.29420069 | T75: 25084 | U75: 1.0274433 | V75: 22.517674 | W75: -0.024719192 | X75: 0.006020774 | Y75: 22.617778 | Z75: 23.965 | AA75: =IF(AND(ISNUMBER(Y75),ISNUMBER(Z75),Y75>0,Z75>0),Y75/Z75,"") -> 0.94378376 | AB75: 15.893032 | AC75: 0.043846103 | AD75: 0.020107177 | AE75: Fiscal year ends June 30. FY2026 (report_date 2026-06-30) already reported, so first two future estimate years are FY2027 and FY2028. FY2026 total_equity 54541000000 (stockholders 54311000000). FY2026 balance sheet total_liabilities_and_equity 126751000000 vs total_assets 126521000000 as returned.
A76: QCOM | B76: Qualcomm Inc. | C76: Technology | D76: Semiconductors | E76: USD | F76: STD | G76: 2025-09-28 | H76: 5 | I76: 44284 | J76: 0.00063308328 | K76: 0.13659463 | L76: 0.27899467 | M76: 5 | N76: 12820 | O76: 0.28949508 | P76: 5 | Q76: 5 | R76: 0.38884706 | S76: 0.26129397 | T76: 3895 | U76: 0.2609016 | V76: 18.606928 | W76: -0.028144239 | X76: 0.062844368 | Y76: 20.074032 | Z76: 17.165379 | AA76: =IF(AND(ISNUMBER(Y76),ISNUMBER(Z76),Y76>0,Z76>0),Y76/Z76,"") -> 1.1694488 | AB76: 14.532732 | AC76: 0.056283688 | AD76: 0.016975932 | AE76: Fiscal year ends September. Estimates returned start at FY2027 (no FY2026 record returned), so FY2027 and FY2028 used. FY2025 net income depressed by tax (income_tax 7122000000); FY2024 net income 10142000000 (net_income) vs 10110000000 continuing.
A77: RTX | B77: RTX Corp. | C77: Industrials | D77: Aerospace | E77: USD | F77: STD | G77: 2025-12-31 | H77: 5 | I77: 88603 | J77: 0.097231011 | K77: 0.097413857 | L77: 0.10496259 | M77: 5 | N77: 7940 | O77: 0.089613219 | P77: 5 | Q77: 5 | R77: 0.074055781 | S77: 0.10027108 | T77: 32071 | U77: 2.1457915 | V77: 5.0681199 | W77: -0.087152567 | X77: 0.012324639 | Y77: 32.029565 | Z77: 33.486381 | AA77: =IF(AND(ISNUMBER(Y77),ISNUMBER(Z77),Y77>0,Z77>0),Y77/Z77,"") -> 0.95649527 | AB77: 17.139245 | AC77: 0.046172738 | AD77: 0.086480422 | AE77: Goodwill and intangibles about half of total assets (tangible book value negative). EPS estimate for 2026 (7.26) is well above FY2025 reported diluted EPS (4.96) as returned. total_equity includes minority interest (FY2025 total_stockholders_equity 65245000000).
A78: TXN | B78: Texas Instruments Inc. | C78: Technology | D78: Semiconductors | E78: USD | F78: STD | G78: 2025-12-31 | H78: 5 | I78: 17682 | J78: -0.040677565 | K78: 0.13049038 | L78: 0.34062889 | M78: 5 | N78: 2603 | O78: 0.14721185 | P78: 5 | Q78: 5 | R78: 0.18809381 | S78: 0.30731887 | T78: 10510 | U78: 1.2736306 | V78: 11.092081 | W78: -0.014038877 | X78: 0.023696414 | Y78: 42.623298 | Z78: 23.907433 | AA78: =IF(AND(ISNUMBER(Y78),ISNUMBER(Z78),Y78>0,Z78>0),Y78/Z78,"") -> 1.7828471 | AB78: 27.665399 | AC78: 0.020812411 | AD78: 0.24075861 | AE78: FY2026+ are estimates.
A79: UNP | B79: Union Pacific Corp. | C79: Industrials | D79: Railroads | E79: USD | F79: STD | G79: 2025-12-31 | H79: 5 | I79: 24510 | J79: -0.0049152423 | K79: 0.010721649 | L79: 0.40142799 | M79: 5 | N79: 5499 | O79: 0.22435741 | P79: 5 | Q79: 5 | R79: 0.15942264 | S79: 0.38652732 | T79: 30289 | U79: 2.3407264 | V79: 7.5164248 | W79: -0.048878205 | X79: 0 | Y79: 22.772433 | Z79: 20.544144 | AA79: =IF(AND(ISNUMBER(Y79),ISNUMBER(Z79),Y79>0,Z79>0),Y79/Z79,"") -> 1.1084635 | AB79: 14.768391 | AC79: 0.038950133 | AD79: 0.1055549 | AE79: Gross profit definition changed across years (FY2025 gross margin 59% vs ~45% earlier). Estimated SALES for 2026 (27.1B) is above reported FY2025 revenue (24.5B). stock_based_compensation 0 for FY2023-2025.
A80: WM | B80: Waste Management Inc. | C80: Industrials | D80: Waste And Disposal Services | E80: USD | F80: STD | G80: 2025-12-31 | H80: 5 | I80: 25204 | J80: 0.085631525 | K80: 0.14236505 | L80: 0.18278845 | M80: 5 | N80: 2816 | O80: 0.1117283 | P80: 5 | Q80: 5 | R80: 0.11131082 | S80: 0.27104394 | T80: 22706 | U80: 4.4758526 | V80: 5.0515351 | W80: -0.026024096 | X80: 0 | Y80: 29.677504 | Z80: 31.476274 | AA80: =IF(AND(ISNUMBER(Y80),ISNUMBER(Z80),Y80>0,Z80>0),Y80/Z80,"") -> 0.94285313 | AB80: 14.098439 | AC80: 0.042310147 | AD80: 0.047654343 | AE80: FY2025 D&A 735000000 and ebitda 5073000000 differ from prior years (D&A ~2.1-2.4bn) as returned. FY2025 stock_based_compensation 0 and common_stock_repurchased 0 as returned. Analyst EPS (8.11) is adjusted basis vs GAAP 6.70, as returned.
A81: WMT | B81: Walmart Inc. | C81: Consumer Services | D81: Department Stores | E81: USD | F81: STD | G81: 2026-01-31 | H81: 5 | I81: 713163 | J81: 0.052722909 | K81: 0.047252142 | L81: 0.041820734 | M81: 5 | N81: 14923 | O81: 0.02092509 | P81: 5 | Q81: 5 | R81: 0.14495257 | S81: 0.20618761 | T81: 56368 | U81: 1.2129715 | V81: 10.655591 | W81: -0.021945867 | X81: 0 | Y81: 40.823105 | Z81: 33.538462 | AA81: =IF(AND(ISNUMBER(Y81),ISNUMBER(Z81),Y81>0,Z81>0),Y81/Z81,"") -> 1.2172027 | AB81: 20.727225 | AC81: 0.014893139 | AD81: 0.055315684 | AE81: Fiscal year ends January (fiscal_year 2026 = FYE 2026-01-31). total_equity includes minority interest (total_stockholders_equity FY2026 = 99617000000). stock_based_compensation reported as 0 in all years. Estimates are for FY2027 and FY2028 (FYE Jan 2027/2028).
A82: ABBV | B82: AbbVie Inc. | C82: Health Care | D82: Pharmaceuticals | E82: USD | F82: STD | G82: 2025-12-31 | H82: 5 | I82: 61160 | J82: 0.017525049 | K82: 0.085667625 | L82: 0.32849902 | M82: 5 | N82: 17816 | O82: 0.2913015 | P82: 5 | Q82: 5 | R82: 0.26198587 | T82: 63811 | U82: 3.6196608 | V82: 6.9446941 | W82: -0.0022497188 | X82: 0.015614781 | Y82: 78.098321 | Z82: 56.765568 | AA82: =IF(AND(ISNUMBER(Y82),ISNUMBER(Z82),Y82>0,Z82>0),Y82/Z82,"") -> 1.3758045 | AB82: 26.301052 | AC82: 0.036945948 | AD82: 0.10539535 | AE82: Negative total equity in FY2025 (-3228000000) and TTM (negative price_to_book, ROE, debt_to_equity). FY2025 ebitda as returned (17629000000) appears low vs operating_income. FY report ebitda/operating_income as returned. Provider FMP.
A83: ADI | B83: Analog Devices Inc. | C83: Technology | D83: Semiconductors | E83: USD | F83: STD | G83: 2025-11-01 | H83: 5 | I83: 11019.707 | J83: -0.028383892 | K83: 0.16893216 | L83: 0.26611379 | M83: 5 | N83: 4278.65 | O83: 0.38827257 | P83: 5 | Q83: 5 | R83: 0.09615154 | S83: 0.067049871 | T83: 5012.289 | U83: 0.99674188 | V83: 9.2299286 | W83: -0.050592724 | X83: 0.029180449 | Y83: 48.042504 | Z83: 49.568571 | AA83: =IF(AND(ISNUMBER(Y83),ISNUMBER(Z83),Y83>0,Z83>0),Y83/Z83,"") -> 0.96921301 | AB83: 29.201879 | AC83: 0.024910995 | AD83: 0.37035384 | AE83: FY ends ~Nov 1 (FY2026 ends 2026-11-01, not yet reported). FY2026 consensus EPS (12.87) well above FY2025 GAAP EPS (4.56), likely adjusted basis. Tangible book value negative.
A84: ALAB | B84: Astera Labs Inc. | C84: Technology | D84: Semiconductors | E84: USD | F84: STD | G84: 2025-12-31 | H84: 4 | I84: 852.525 | J84: 1.2017644 | K84: 1.1512655 | L84: 0.20342277 | M84: 1 | N84: 281.762 | O84: 0.33050292 | P84: 2 | Q84: 2 | R84: 0.65250956 | S84: 0.16069855 | T84: -1153.669 | U84: -5.127828 | V84: 999 | W84: 0.37637599 | X84: 0.18771649 | Y84: 149.35945 | Z84: 126.0303 | AA84: =IF(AND(ISNUMBER(Y84),ISNUMBER(Z84),Y84>0,Z84>0),Y84/Z84,"") -> 1.1851074 | AB84: 166.01513 | AC84: 0.0049802154 | AD84: 1.2365976 | AE84: Only 4 fiscal years returned (IPO 2024). FY2022 negative equity (-85292000). interest_expense 0 as returned.
A85: AMT | B85: American Tower REIT Inc. | C85: Real Estate | D85: Specialty REITs | E85: USD | F85: UTIL/REIT | G85: 2025-12-31 | H85: 5 | I85: 10645.1 | J85: 0.03341914 | K85: 0.051139505 | L85: 0.45848325 | M85: 5 | N85: 3783.6 | O85: 0.35543114 | P85: 5 | Q85: 5 | R85: 0.07196292 | S85: 0.24430002 | T85: 43489.1 | U85: 7.1250389 | V85: 4.7947736 | W85: 0.013814926 | X85: 0.016364337 | Y85: 24.837898 | Z85: 51.405975 | AA85: =IF(AND(ISNUMBER(Y85),ISNUMBER(Z85),Y85>0,Z85>0),Y85/Z85,"") -> 0.48317142 | AB85: 18.14469 | AC85: 0.04715957 | AD85: 0.035806184 | AE85: REIT. total_equity is 10355300000 incl. minority interest 6702800000 (stockholders equity 3652500000). Estimate EPS (6.97 FY2026) is on a different basis than GAAP eps_diluted (5.39 FY2025), likely AFFO-style, as returned. FY2025 ebitda (6103700000) vs FY2024 (7154100000) as returned. Provider FMP.
A86: AMZN | B86: Amazon.com Inc. | C86: Consumer Services | D86: Internet & Direct Marketing Retail | E86: USD | F86: STD | G86: 2025-12-31 | H86: 5 | I86: 716924 | J86: 0.11731284 | K86: 0.12377755 | L86: 0.11155297 | M86: 4 | N86: 7695 | O86: 0.010733355 | P86: 3 | Q86: 5 | R86: 0.1432584 | S86: 0.18894822 | T86: 29958 | U86: 0.18118918 | V86: 35.169305 | W86: 0.062616547 | X86: 0.027153506 | Y86: 20.648413 | Z86: 44.641348 | AA86: =IF(AND(ISNUMBER(Y86),ISNUMBER(Z86),Y86>0,Z86>0),Y86/Z86,"") -> 0.46254008 | AB86: 11.562377 | AC86: -0.0041639949 | AD86: 0.15593081 | AE86: FY2022 net loss. TTM price_to_free_cash_flow negative (-240.7462113548387) as returned. EPS estimate drops from 12.78 (2026) to 10.64 (2027) as returned (possible one-off gains in 2026 consensus).
A87: BLK | B87: BlackRock Inc. | C87: Financials | D87: Other Diversified Financial Services | E87: USD | F87: FIN | G87: 2025-12-31 | H87: 5 | I87: 24216 | J87: 0.10654306 | K87: 0.18665164 | L87: 0.29084077 | M87: 5 | N87: 3552 | O87: 0.14667988 | P87: 5 | Q87: 5 | R87: 0.089336555 | S87: 0.090231062 | T87: 739 | U87: 0.091133309 | V87: 9.9759207 | W87: 0.055493984 | X87: 0.05397258 | Y87: 25.368483 | Z87: 23.621259 | AA87: =IF(AND(ISNUMBER(Y87),ISNUMBER(Z87),Y87>0,Z87>0),Y87/Z87,"") -> 1.0739683 | AB87: 15.853369 | AC87: 0.013925139 | AD87: 0.19942529 | AE87: Asset manager format: large other_non_current_liabilities and other_non_current_assets (separate-account/consolidated items); current_ratio FY 15.76 vs TTM 1.35 (not comparable). Net income FY2025 (5.553B) is below FY2024 (6.369B). FY2025 diluted shares 160.9M vs 151.6M FY2024. EPS estimate for 2026 (56.05) is well above FY2025 diluted EPS (35.31) as returned; SBC to revenue 5.4%. total_equity includes minority interest (FY2025 total_stockholders_equity 55888000000). FY2021 total_assets 152.6B (includes consolidated funds).
A88: BRK-B | B88: Berkshire Hathaway Inc. | C88: Financials | D88: Reinsurance | E88: USD | F88: FIN | G88: 2025-12-31 | H88: 5 | I88: 371444 | J88: 0.071402235 | K88: 2.9615032e-05 | L88: 0.15851649 | M88: 4 | N88: 25042 | O88: 0.067417969 | P88: 5 | Q88: 5 | R88: 0.095839257 | S88: 0.093049494 | T88: -234357 | U88: -3.2389436 | V88: 11.615703 | W88: -0.02086811 | X88: 0 | Y88: 13.030578 | Z88: 9.5198762 | AA88: =IF(AND(ISNUMBER(Y88),ISNUMBER(Z88),Y88>0,Z88>0),Y88/Z88,"") -> 1.3687759 | AB88: 15.858275 | AC88: 0.021531735 | AD88: 0.086359047 | AE88: Insurance/conglomerate; stock_based_compensation, dividends 0 as returned. TTM key_metrics per-share values (book_value_per_share etc.) appear in Class A units; not copied. Resolved via 'Berkshire Hathaway' (listing XNYS:BRK.B). fy_market_cap/FY key metrics per returned key_metrics FY rows.
A89: COIN | B89: Coinbase Global Inc. | C89: Financials | D89: Financial Services | E89: USD | F89: FIN | G89: 2025-12-31 | H89: 5 | I89: 7181.325 | J89: 0.31002765 | K89: 0.094042408 | L89: 0.20276829 | M89: 4 | N89: 2426.383 | O89: 0.337874 | P89: 4 | Q89: 4 | R89: 0.10740487 | S89: 0.085197192 | T89: -4082.607 | U89: -2.2732855 | V89: 17.048283 | W89: 0.29176749 | X89: 0.11689208 | Y89: -49.256098 | Z89: 35.227989 | AA89: =IF(AND(ISNUMBER(Y89),ISNUMBER(Z89),Y89>0,Z89>0),Y89/Z89,"") | AB89: -71.253193 | AC89: 0.055485172 | AD89: -0.27443675 | AE89: Crypto exchange; balance sheet includes customer custody items (FY2022 total_assets 89.7B, FY2023 deferred_revenue anomaly in source). capex reported as 0 for FY2023-2025 so free_cash_flow equals operating_cash_flow. TTM net_margin negative (-0.157) while FY2025 positive (0.176); ttm values as returned. EPS in 2026 estimate negative.
A90: CRDO | B90: Credo Technology Group Holding Ltd. | C90: Telecommunications | D90: Alternative Carriers | E90: USD | F90: STD | G90: 2026-05-02 | H90: 5 | I90: 1335.116 | J90: 0.93529797 | K90: 2.0567592 | L90: 0.33330812 | M90: 2 | N90: 406.996 | O90: 0.30483943 | P90: 3 | Q90: 3 | R90: 0.54439161 | S90: 0.22886037 | T90: -1417.838 | U90: -2.7796821 | V90: 999 | W90: 0.28436911 | X90: 0.1367956 | Y90: 68.081356 | Z90: 104.22416 | AA90: =IF(AND(ISNUMBER(Y90),ISNUMBER(Z90),Y90>0,Z90>0),Y90/Z90,"") -> 0.65322046 | AB90: 62.789231 | AC90: 0.011710868 | AD90: 0.87399873 | AE90: FY ends ~end of April/early May. Resolved via name 'Credo Technology' (ticker query failed); rp entity listed under XNAS:CRDO, sector classified Telecommunications/Alternative Carriers by provider. interest_expense 0 as returned.
A91: CRWD | B91: CrowdStrike Holdings Inc. | C91: Technology | D91: Software | E91: USD | F91: STD | G91: 2026-01-31 | H91: 5 | I91: 4812.005 | J91: 0.29006867 | K91: 0.21711245 | L91: -0.060950061 | M91: 1 | N91: 1310.241 | O91: 0.27228588 | P91: 5 | Q91: 5 | R91: -0.015686365 | S91: -0.036332741 | T91: -4410.048 | U91: -24.166898 | V91: -10.466864 | W91: 0.10720643 | X91: 0.22790479 | Y91: 7552.4148 | Z91: 790.59459 | AA91: =IF(AND(ISNUMBER(Y91),ISNUMBER(Z91),Y91>0,Z91>0),Y91/Z91,"") -> 9.5528287 | AB91: 610.05197 | AC91: 0.0058106871 | AD91: 0.24806213 | AE91: FY ends Jan 31. total_equity includes minority interest (stockholders equity FY2026 4428390000). TTM net income positive (net_margin 0.0108) while FY2026 net loss; TTM ratios as returned. Estimate EPS is non-GAAP basis vs GAAP reported loss.
A92: CVX | B92: Chevron Corp. | E92: USD | F92: STD | G92: 2025-12-31 | H92: 5 | I92: 184432 | J92: -0.078528749 | K92: -0.046439244 | L92: 0.090407305 | M92: 5 | N92: 16592 | O92: 0.089962696 | P92: 5 | Q92: 5 | R92: 0.077589842 | S92: 0.063998626 | T92: 34461 | U92: 0.83863039 | V92: 13.700904 | W92: -0.043435551 | X92: 0 | Y92: 20.7383 | Z92: 14.398773 | AA92: =IF(AND(ISNUMBER(Y92),ISNUMBER(Z92),Y92>0,Z92>0),Y92/Z92,"") -> 1.4402824 | AB92: 8.2789708 | AC92: 0.062530958 | AD92: 0.3133724 | AE92: Sector and industry null (company_overview section not requested). stock_based_compensation 0 in FY2021, FY2023-FY2025 as returned. FY2025 balance sheet (total_assets 324012000000, total_equity 192176000000) steps up from FY2024 as returned. TTM ratios and key metrics differ from FY2025 as returned.
A93: DDOG | B93: Datadog Inc. | C93: Technology | D93: Application Software | E93: USD | F93: STD | G93: 2025-12-31 | H93: 5 | I93: 3427.158 | J93: 0.26949539 | K93: 0.27675369 | L93: -0.012947463 | M93: 3 | N93: 1000.557 | O93: 0.29194948 | P93: 5 | Q93: 5 | R93: 0.0023252123 | S93: 0.028867914 | T93: -2939.644 | U93: -15.165625 | V93: -4.0123881 | W93: 0.15237627 | X93: 0.21903601 | Y93: 571.82241 | Z93: 438.67742 | AA93: =IF(AND(ISNUMBER(Y93),ISNUMBER(Z93),Y93>0,Z93>0),Y93/Z93,"") -> 1.3035146 | AB93: 343.76673 | AC93: 0.011292647 | AD93: 0.30519519 | AE93: FY2021 eps_diluted returned as -0.0671. Estimate EPS (non-GAAP basis) not comparable to reported GAAP EPS 0.30.
A94: DE | B94: Deere & Co. | C94: Industrials | D94: Commercial Vehicles and Trucks | E94: USD | F94: STD | G94: 2025-11-02 | H94: 5 | I94: 44665 | J94: -0.045005667 | K94: -0.11585969 | L94: 0.18842494 | M94: 5 | N94: 3231 | O94: 0.07233852 | P94: 5 | Q94: 5 | R94: 0.2211131 | S94: 0.19329411 | T94: 54249 | U94: 4.6541695 | V94: 2.6548896 | W94: -0.11296115 | X94: 0.0033807232 | Y94: 35.407428 | Z94: 16.900939 | AA94: =IF(AND(ISNUMBER(Y94),ISNUMBER(Z94),Y94>0,Z94>0),Y94/Z94,"") -> 2.0949976 | AB94: 19.477045 | AC94: 0.022408169 | AD94: -0.072848524 | AE94: Fiscal year ends late Oct/early Nov. Includes large captive-finance (John Deere Financial) balance sheet: total_debt and interest_expense reflect financing operations. FY2025 EPS 18.5 and revenue below FY2024 as returned; FY2026 SALES estimate 41411220680 below FY2025 revenue as returned. Tearsheet source FMP.
A95: ELV | B95: Elevance Health Inc. | C95: Health Care | D95: Managed Health Care | E95: USD | F95: STD | G95: 2025-12-31 | H95: 5 | I95: 199125 | J95: 0.083384537 | K95: 0.12620892 | L95: 0.04073823 | M95: 5 | N95: 3174 | O95: 0.015939736 | P95: 5 | Q95: 5 | R95: 0.094562196 | S95: 0.12860582 | T95: 23744 | U95: 2.45848 | V95: 5.78602 | W95: -0.086490939 | X95: 0.001386064 | Y95: 18.873111 | Z95: 18.35802 | AA95: =IF(AND(ISNUMBER(Y95),ISNUMBER(Z95),Y95>0,Z95>0),Y95/Z95,"") -> 1.0280581 | AB95: 13.275069 | AC95: 0.068290064 | AD95: -0.010258422 | AE95: Managed-care format: gross_profit = revenue minus cost of revenue (benefit expense). FY2025 EPS 25.12 GAAP vs FY2026 consensus 27.24 (likely adjusted basis). total_equity includes minority interest. FY2022 and FY2021 net_income from net_income field (5894000000, 6104000000); cash-flow net income in FY2022 6019000000 differs.
A96: FISV | B96: Fiserv Inc. | C96: Industrials | D96: Financial Administration | E96: USD | F96: STD | G96: 2025-12-31 | H96: 5 | I96: 21193 | J96: 0.061135288 | K96: 0.036028549 | L96: 0.27452461 | M96: 5 | N96: 6062 | O96: 0.28603784 | P96: 5 | Q96: 5 | R96: 0.085075798 | S96: 0.13474793 | T96: 28199 | U96: 3.1620318 | V96: 3.896852 | W96: -0.15264701 | X96: 0.016845185 | Y96: 12.245681 | Z96: 26.462151 | AA96: =IF(AND(ISNUMBER(Y96),ISNUMBER(Z96),Y96>0,Z96>0),Y96/Z96,"") -> 0.46276212 | AB96: 8.732655 | AC96: 0.20687776 | AD96: -0.037644162 | AE96: FY2025 data incomplete as returned: gross_profit=0, cost_of_revenue=0, capex=0 (FY2025 free_cash_flow equals operating_cash_flow), no market-cap-consistent TTM; FY2025 market_cap 35.3B vs FY2024 118.9B (large price drop). TTM gross_margin 0.166 and ttm free_cash_flow_yield 0.207 look anomalous. Fiserv listed XNYS:FI (ticker changed from FISV). Copied as returned.
A97: HON | B97: Honeywell International Inc. | C97: Industrials | D97: Diversified Industrials | E97: USD | F97: STD | G97: 2025-12-31 | H97: 5 | I97: 37442 | J97: 0.018237162 | K97: 0.078491805 | L97: 0.17539127 | M97: 5 | N97: 5393 | O97: 0.14403611 | P97: 5 | Q97: 5 | R97: 0.13987409 | S97: 0.30628238 | T97: 21650 | U97: 2.6376706 | V97: 4.8861607 | W97: -0.058995755 | X97: 0 | Y97: 8.0421381 | Z97: 12.865793 | AA97: =IF(AND(ISNUMBER(Y97),ISNUMBER(Z97),Y97>0,Z97>0),Y97/Z97,"") -> 0.6250791 | AB97: 6.9853654 | AC97: 0.062708843 | AD97: -0.46186665 | AE97: Estimate scale as returned (SALES FY2026 20148788978, EPS FY2026 8.31136) differs from FY2025 reported revenue 37442000000 and eps_diluted 14.72. stock_based_compensation is 0 for FY2025 as returned. TTM net_margin 0.2273 vs FY2025 0.1263 as returned. Provider FMP.
A98: INTC | B98: Intel Corp. | C98: Technology | D98: Data Processing & Outsourced Services | E98: USD | F98: STD | G98: 2025-12-27 | H98: 5 | I98: 52853 | J98: -0.05712888 | K98: -0.0046703452 | L98: -0.04188977 | M98: 3 | N98: -4949 | O98: -0.093637069 | P98: 1 | Q98: 5 | R98: 0.00046220305 | S98: -0.0021130104 | T98: 9169 | U98: 0.63877665 | V98: -2.0293309 | W98: 0.17778317 | X98: 0.046052258 | Y98: -47.530806 | Z98: 13.553846 | AA98: =IF(AND(ISNUMBER(Y98),ISNUMBER(Z98),Y98>0,Z98>0),Y98/Z98,"") | AB98: 148.11501 | AC98: 0.0055924819 | AD98: 0.19694299 | AE98: total_equity includes minority interest (FY2025 stockholders equity 114281000000). Net loss FY2025/FY2024; TTM net_margin -0.198 vs FY2025 -0.005 (as returned). Estimate EPS likely non-GAAP vs GAAP reported loss. Industry label as returned by Bigdata.
A99: KKR | B99: KKR & Co. Inc. | C99: Financials | D99: Asset Management & Custody Banks | E99: USD | F99: FIN | G99: 2025-12-31 | H99: 5 | I99: 19207.544 | J99: 0.51124229 | K99: -0.11241736 | L99: 0.025521118 | M99: 4 | N99: 316.995 | O99: 0.016503672 | P99: 2 | Q99: 2 | R99: 0.0092681917 | S99: 0.029038436 | T99: 54759.678 | U99: 5.3838634 | V99: 0.15957408 | W99: 0.27518434 | X99: 0.037595072 | Y99: 27.391369 | Z99: 31.082727 | AA99: =IF(AND(ISNUMBER(Y99),ISNUMBER(Z99),Y99>0,Z99>0),Y99/Z99,"") -> 0.88124085 | AB99: 12.595813 | AC99: 0.028316126 | AD99: -0.40755889 | AE99: Asset manager / insurer (Global Atlantic) consolidated format: total_assets 410bn, equity includes minority_interest 50729350000 (FY2025 stockholders equity 30902561000, preferred 2543404000). Cash and short-term investments FY2025 is 6155000 (FY2024 112557690000) as returned; balance sheet classifications changed between FY2024 and FY2025. operating_income, ebitda, interest_expense and FCF are not comparable to industrial definitions (ebitda equals ebit as returned). net_income = bottom_line_net_income (attributable to common); continuing ops FY2025 6145412000. Estimate EPS/sales bases differ from reported GAAP (adjusted vs GAAP); SALES FY2029 estimate based on 1 analyst. FY2026+ are estimates.
A100: LOW | B100: Lowe's Companies Inc. | C100: Consumer Services | D100: Home Improvement Retailers | E100: USD | F100: STD | G100: 2026-01-30 | H100: 5 | I100: 86286 | J100: -0.038458186 | K100: 0.031216387 | L100: 0.11766683 | M100: 5 | N100: 7651 | O100: 0.088670236 | P100: 5 | Q100: 5 | R100: 0.2400883 | T100: 43325 | U100: 3.4748957 | V100: 6.6489849 | W100: -0.11251981 | X100: 0.0028625733 | Y100: 15.673142 | Z100: 20.416667 | AA100: =IF(AND(ISNUMBER(Y100),ISNUMBER(Z100),Y100>0,Z100>0),Y100/Z100,"") -> 0.76766409 | AB100: 11.147624 | AC100: 0.067275091 | AD100: 0.068253502 | AE100: Fiscal year ends ~Jan 31; provider labels FY ended 2026-01-30 as fiscal_year 2025; estimates fiscal_year 2027 and 2028 are the first two future FYs as labeled (no 2026 estimate returned). Negative total equity in all years FY2021-FY2025 (negative price_to_book, ROE, debt_to_equity TTM). goodwill_and_intangible_assets is 0 for FY2023-FY2024 as returned. Provider FMP.
A101: MDLZ | B101: Mondelez International Inc. | C101: Consumer Goods | D101: Food Products | E101: USD | F101: STD | G101: 2025-12-31 | H101: 5 | I101: 38537 | J101: 0.069565782 | K101: 0.057517631 | L101: 0.093935698 | M101: 5 | N101: 3235 | O101: 0.083945299 | P101: 5 | Q101: 5 | R101: 0.064664096 | S101: 0.0946661 | T101: 20278 | U101: 4.3571122 | V101: 6.0434057 | W101: -0.062815884 | X101: 0.002958196 | Y101: 22.568015 | Z101: 21.669935 | AA101: =IF(AND(ISNUMBER(Y101),ISNUMBER(Z101),Y101>0,Z101>0),Y101/Z101,"") -> 1.0414436 | AB101: 15.971725 | AC101: 0.039376467 | AD101: 0.04305062 | AE101: FY2025 margins sharply lower than FY2024 (gross_profit 10.9B vs 14.3B). TTM figures differ from FY2025 (TTM gross_margin 0.311, net_margin 0.0886 vs FY 0.284, 0.0636). fy_market_cap FY2025 69.656B vs TTM enterprise_value 98.7B.
...

Sheet Raw_FY
A1: ticker | B1: fiscal_year | C1: report_date | D1: revenue | E1: gross_profit | F1: operating_income | G1: ebitda | H1: net_income | I1: eps_diluted | J1: shares_diluted | K1: interest_expense | L1: operating_cash_flow | M1: capex | N1: free_cash_flow | O1: stock_based_compensation | P1: total_debt | Q1: cash_and_short_term_investments | R1: total_equity | S1: fy_pe_ratio
A2: ABNB | B2: 2025 | C2: 2025-12-31 | D2: 12305000000 | E2: 8892000000 | F2: 2609000000 | G2: 2700000000 | H2: 2511000000 | I2: 4.03 | J2: 623000000 | K2: 0 | L2: 4646000000 | M2: 0 | N2: 4646000000 | O2: 1592000000 | P2: 2271000000 | Q2: 11014000000 | R2: 8199000000 | S2: 33.102439
A3: ABNB | B3: 2024 | C3: 2024-12-31 | D3: 11102000000 | E3: 9224000000 | F3: 2553000000 | G3: 3396000000 | H3: 2648000000 | I3: 4.11 | J3: 645000000 | K3: 0 | L3: 4518000000 | M3: 0 | N3: 4518000000 | O3: 1407000000 | P3: 2294000000 | Q3: 10611000000 | R3: 8412000000 | S3: 31.362768
A4: ABNB | B4: 2023 | C4: 2023-12-31 | D4: 9917000000 | E4: 8214000000 | F4: 1518000000 | G4: 2229000000 | H4: 4792000000 | I4: 7.24 | J4: 662000000 | K4: 83000000 | L4: 3884000000 | M4: 0 | N4: 3884000000 | O4: 1120000000 | P4: 2304000000 | Q4: 10071000000 | R4: 8165000000 | S4: 18.103723
A5: ABNB | B5: 2022 | C5: 2022-12-31 | D5: 8399000000 | E5: 6900000000 | F5: 1802000000 | G5: 1972000000 | H5: 1893000000 | I5: 2.79 | J5: 680000000 | K5: 24000000 | L5: 3430000000 | M5: -25000000 | N5: 3405000000 | O5: 930000000 | P5: 2341000000 | Q5: 9622000000 | R5: 5560000000 | S5: 28.787879
A6: ABNB | B6: 2021 | C6: 2021-12-31 | D6: 5992000000 | E6: 4836000000 | F6: 429000000 | G6: 276000000 | H6: -352000000 | I6: -0.57 | J6: 616000000 | K6: 438000000 | L6: 2313000000 | M6: 0 | N6: 2313000000 | O6: 0 | P6: 2418000000 | Q6: 8322000000 | R6: 4775000000 | S6: -292.08772
A7: ADBE | B7: 2025 | C7: 2025-11-28 | D7: 23769000000 | E7: 21218000000 | F7: 8706000000 | G7: 9815000000 | H7: 7130000000 | I7: 16.7 | J7: 427000000 | K7: 263000000 | L7: 10031000000 | M7: -179000000 | N7: 9852000000 | O7: 1942000000 | P7: 6648000000 | Q7: 6595000000 | R7: 11623000000 | S7: 19.135087
A8: ADBE | B8: 2024 | C8: 2024-11-29 | D8: 21505000000 | E8: 19147000000 | F8: 6741000000 | G8: 7957000000 | H8: 5560000000 | I8: 12.36 | J8: 450000000 | K8: 164000000 | L8: 8056000000 | M8: -183000000 | N8: 7873000000 | O8: 1833000000 | P8: 6056000000 | Q8: 7886000000 | R8: 14105000000 | S8: 41.473473
A9: ADBE | B9: 2023 | C9: 2023-12-01 | D9: 19409000000 | E9: 17055000000 | F9: 6650000000 | G9: 7784000000 | H9: 5428000000 | I9: 11.83 | J9: 459000000 | K9: 113000000 | L9: 7302000000 | M9: -360000000 | N9: 6942000000 | O9: 1718000000 | P9: 4080000000 | Q9: 7842000000 | R9: 16518000000 | S9: 51.554714
A10: ADBE | B10: 2022 | C10: 2022-12-02 | D10: 17606000000 | E10: 15441000000 | F10: 6098000000 | G10: 6954000000 | H10: 4756000000 | I10: 10.1 | J10: 471000000 | K10: 112000000 | L10: 7838000000 | M10: -442000000 | N10: 7396000000 | O10: 1440000000 | P10: 4633000000 | Q10: 6096000000 | R10: 14051000000 | S10: 33.714709
A11: ADBE | B11: 2021 | C11: 2021-12-03 | D11: 15785000000 | E11: 13920000000 | F11: 5802000000 | G11: 6602000000 | H11: 4822000000 | I11: 10.02 | J11: 481000000 | K11: 113000000 | L11: 7230000000 | M11: -330000000 | N11: 6893000000 | O11: 1069000000 | P11: 4673000000 | Q11: 5798000000 | R11: 14797000000 | S11: 61.042574
A12: ADP | B12: 2026 | C12: 2026-06-30 | D12: 21947500000 | E12: 10575600000 | F12: 4078400000 | G12: 6448400000 | H12: 4413500000 | I12: 10.95 | J12: 399429000 | K12: 459200000 | L12: 5441200000 | M12: -196600000 | N12: 5244600000 | O12: 242600000 | P12: 5270800000 | Q12: 4230100000 | R12: 6031200000 | S12: 20.414768
A13: ADP | B13: 2025 | C13: 2025-06-30 | D13: 20560900000 | E13: 10452200000 | F13: 5411900000 | G13: 6242000000 | H13: 4079700000 | I13: 9.98 | J13: 408700000 | K13: 455900000 | L13: 4939700000 | M13: -168700000 | N13: 4771000000 | O13: 266100000 | P13: 9065400000 | Q13: 7846600000 | R13: 6188000000 | S13: 30.778443
... A275: ARM | B275: 2023 | C275: 2023-03-31 | D275: 2679000000 | E275: 2484000000 | F275: 678000000 | G275: 841000000 | H275: 524000000 | I275: 0.51 | J275: 1026054856 | K275: 0 | L275: 739000000 | M275: -93000000 | N275: 646000000 | O275: 79000000 | P275: 219000000 | Q275: 2215000000 | R275: 4051000000 | S275: 119.11765
A276: ARM | B276: 2022 | C276: 2022-03-31 | D276: 2703000000 | E276: 2483000000 | F276: 680000000 | G276: 971000000 | H276: 549000000 | I276: 0.54 | J276: 1026054856 | K276: 0 | L276: 458000000 | M276: -75000000 | N276: 383000000 | O276: 26000000 | S276: 112.5
A277: AVGO | B277: 2025 | C277: 2025-11-02 | D277: 63887000000 | E277: 43294000000 | F277: 25484000000 | G277: 34714000000 | H277: 23126000000 | I277: 4.77 | J277: 4853000000 | K277: 3210000000 | L277: 27537000000 | M277: -623000000 | N277: 26914000000 | O277: 7568000000 | P277: 65136000000 | Q277: 16178000000 | R277: 81292000000 | S277: 73.839104
A278: AVGO | B278: 2024 | C278: 2024-11-03 | D278: 51574000000 | E278: 32509000000 | F278: 13463000000 | G278: 23879000000 | H278: 5895000000 | I278: 1.23 | J278: 4778000000 | K278: 3953000000 | L278: 19962000000 | M278: -548000000 | N278: 19414000000 | O278: 5741000000 | P278: 67566000000 | Q278: 9348000000 | R278: 67678000000 | S278: 132.71654
A279: AVGO | B279: 2023 | C279: 2023-10-29 | D279: 35819000000 | E279: 24690000000 | F279: 16207000000 | G279: 20554000000 | H279: 14082000000 | I279: 3.3 | J279: 4270000000 | K279: 1622000000 | L279: 18085000000 | M279: -452000000 | N279: 17633000000 | O279: 2171000000 | P279: 39648000000 | Q279: 14189000000 | R279: 23988000000 | S279: 24.817109
A280: AVGO | B280: 2022 | C280: 2022-10-30 | D280: 33203000000 | E280: 22095000000 | F280: 14225000000 | G280: 19155000000 | H280: 11495000000 | I280: 2.65 | J280: 4230000000 | K280: 1737000000 | L280: 16736000000 | M280: -424000000 | N280: 16312000000 | O280: 1533000000 | P280: 39978000000 | Q280: 12416000000 | R280: 22709000000 | S280: 17.156934
A281: AVGO | B281: 2021 | C281: 2021-10-31 | D281: 27450000000 | E281: 16844000000 | F281: 8519000000 | G281: 14691000000 | H281: 6736000000 | I281: 1.5 | J281: 4290000000 | K281: 1885000000 | L281: 13764000000 | M281: -443000000 | N281: 13321000000 | O281: 1704000000 | P281: 40273000000 | Q281: 12163000000 | R281: 24989000000 | S281: 33.636943
A282: BMY | B282: 2025 | C282: 2025-12-31 | D282: 48195000000 | E282: 34259000000 | F282: 13724000000 | G282: 15230000000 | H282: 7054000000 | I282: 3.45 | J282: 2041000000 | K282: 1891000000 | L282: 14156000000 | M282: -1311000000 | N282: 12845000000 | O282: 553000000 | P282: 47139000000 | Q282: 10673000000 | R282: 18506000000 | S282: 15.589595
A283: BMY | B283: 2024 | C283: 2024-12-31 | D283: 48300000000 | E283: 34332000000 | F283: 5887000000 | G283: 3168000000 | H283: -8948000000 | I283: -4.41 | J283: 2027000000 | K283: 1947000000 | L283: 15190000000 | M283: -1248000000 | N283: 13942000000 | O283: 507000000 | P283: 51200000000 | Q283: 10859000000 | R283: 16388000000 | S283: -12.825397
A284: BMY | B284: 2023 | C284: 2023-12-31 | D284: 45006000000 | E284: 34313000000 | F284: 8195000000 | G284: 19366000000 | H284: 8025000000 | I284: 3.86 | J284: 2078000000 | K284: 1166000000 | L284: 13860000000 | M284: -1209000000 | N284: 12651000000 | O284: 518000000 | P284: 41464000000 | Q284: 12280000000 | R284: 29485000000 | S284: 13.224227
A285: BMY | B285: 2022 | C285: 2022-12-31 | D285: 46159000000 | E285: 36022000000 | F285: 9104000000 | G285: 19221000000 | H285: 6327000000 | I285: 2.95 | J285: 2146000000 | K285: 1232000000 | L285: 13066000000 | M285: -1118000000 | N285: 11948000000 | O285: 457000000 | P285: 40717000000 | Q285: 9253000000 | R285: 31118000000 | S285: 24.225589
A286: BMY | B286: 2021 | C286: 2021-12-31 | D286: 46385000000 | E286: 36445000000 | F286: 8537000000 | G286: 20118000000 | H286: 6994000000 | I286: 3.12 | J286: 2245000000 | K286: 1334000000 | L286: 16207000000 | M286: -973000000 | N286: 15234000000 | O286: 583000000 | P286: 45596000000 | Q286: 17221000000 | R286: 36006000000 | S286: 19.793651
A287: BX | B287: 2025 | C287: 2025-12-31 | D287: 13828896000 | E287: 11899653000 | F287: 7178286000 | G287: 7214309000 | H287: 3019214000 | I287: 3.88 | J287: 780924000 | K287: 508314000 | L287: 1860601000 | M287: -115703000 | N287: 1744898000 | O287: 1948679000 | P287: 13306165000 | Q287: 2631241000 | R287: 21881172000 | S287: 39.726804
A288: BX | B288: 2024 | C288: 2024-12-31 | D288: 11374228000 | E288: 10930540000 | F288: 6459480000 | G288: 6495445000 | H288: 2776508000 | I288: 3.62 | J288: 766646508 | K288: 443688000 | L288: 3481662000 | M288: -61409000 | N288: 3420253000 | O288: 0 | P288: 12286698000 | Q288: 1972140000 | R288: 19495015000 | S288: 47.629834
... A600: XOM | B600: 2021 | C600: 2021-12-31 | D600: 276692000000 | E600: 64886000000 | F600: 24019000000 | G600: 52788000000 | H600: 23040000000 | I600: 5.39 | J600: 4275000000 | K600: 947000000 | L600: 48129000000 | M600: -12076000000 | N600: 36053000000 | O600: 612000000 | P600: 47704000000 | Q600: 6802000000 | R600: 175683000000 | S600: 11.352505
A602: ערכים גולמיים כפי שהוחזרו מ־Bigdata.com (ספק FMP), במטבע הדיווח, כולל שנים עתידיות אם הספק החזיר אותן (לא נכללו בחישוב: רק שנים עם תאריך דוח עד 13.10.2026).
